Workbook

Sheet README
A1: Personality Panic - Balance Lock v6
A3: Purpose | B3: Master stat/action/job/audio data workbook for the first playable MVP. Send together with Personality_Panic_MVP_Master_Manual_v2.docx.
A4: Core loop | B4: Choose personality -> move map -> enter building -> take action -> stats/costs/time change -> upkeep/rent/pet consequences -> final score.
A5: End condition | B5: When one player maxes all 4 main stats, finish the current round; highest final score wins. Podium screen shows 1st-4th.
A6: Main stats | B6: Connection, Health, Career, Happiness
A7: Upkeep stats | B7: Coolness Factor, Critical Thinking, Enlightenment, Money
A8: Pet stats | B8: Pet Happiness, Pet Health
A9: Money rule | B9: Money and cash are the same resource/stat.
A10: Scaling | B10: T = stat target. Short T=100, Medium T=500, Long T=1000. Action gains/costs scale as % of T.
A12: WHAT CHANGED IN v2
A13: 1. Balance Patch | B13: Weakness penalties unified (main -10%, upkeep -8%), closing the v1 net-budget spread from 27 points (-2 to +25) down to 15 points (+2 to +17). Career/Money-strength types remain intentionally lowest, offset by their income/job snowball. See Balance_Audit sheet.
A14: 2. Job pay now scales with T | B14: v1 locked job pay as static, but rent/items/travel costs scale with T, which starved the economy in Medium/Long games. Dollar values in Jobs_Named are the Short (T=100) baseline; Medium = x5, Long = x10.
A15: 3. Jobs consolidated | B15: Jobs_Named (detailed per-building jobs from the Master Manual) is canonical. Jobs_Tiers keeps the generic 4-tier math as a fallback/reference.
A16: 4. Audio added | B16: Audio_Music and Audio_SFX sheets define every music and sound-effect cue, including the rent-due overmap swap every 4 turns.
A18: Sheets | B18: Settings | Personalities | Balance_Audit | Actions_Master | Items_Mall | Jobs_Named | Jobs_Tiers | Pets | Audio_Music | Audio_SFX
A20: WHAT CHANGED IN v3
A21: 1. Weekend Update card system | B21: New Cards sheet: status cards, investment outcome cards, and standing-based event cards shown at the start of each turn. Draw weights and investment resolution odds are in the same sheet.
A22: 2. Hunger/stress penalties quantified | B22: Previously the docs said 'time penalty' with no number. Now locked: Hunger -4 Time Units, Stress -2 Time Units, penalties stack, minimum 1 Time Unit per turn.
A23: 3. Pet death rework | B23: Old Healthy->Hungry->Sick->Critical->Dead states replaced: miss 1 feeding = Sad Pet, miss 2 consecutive = Starving Pet (final warning), miss 3 consecutive = pet dies (tombstone in housing, owner Happiness -> 0). Feeding resets the counter. Re-adoption allowed.
A25: WHAT CHANGED IN v4
A26: 1. Game length scaling FIXED | B26: Stat cap (T) and gain/economy base (B) are now separate. v3 scaled both by the same multiplier, so Short/Medium/Long took the same number of turns and only changed the size of the numbers. Now Medium takes ~2x and Long ~2.9x the turns of Short. See Settings.
A27: 2. Investment system rebuilt | B27: New Investments sheet defines the full asset lifecycle. Purchases no longer grant free Money (v3 double-counting bug), savings/bonds now cost a real principal and are capped at one holding each, and a Cash Out action was added.
A28: 3. Crypto/Stocks odds retuned | B28: Crypto is now extreme by standing (leader trap / trailer comeback). Stocks are mild, with a new SIDEWAYS MARKET flat outcome that dominates for 2nd/3rd place, plus a MARKET CRASH big-loss card.
A29: 4. Mall prices raised and housing-gated | B29: Electronics, appliances, and furniture cost roughly 2-3x more, and many now require Luxury housing. Recurring costs (food, rent, pet upkeep) unchanged so survival is no harder, only accumulation slower.
A30: 5. Pet shop actions reworked | B30: Bribe Inspector: money cost + Critical Thinking gain. Contact P.I.T.A.: big one-time Happiness gain, once per game.
A31: 6. Read Tiny Print defined | B31: Grants INFORMED: downgrades the next Big Loss to a Small Loss, then is consumed.
A32: 7. Card modifier rule locked | B32: Card effects ignore personality/pet/item modifiers and the income cap.
A33: 8. Weekend Cards toggle is now three-way | B33: Full / Essential / Off (debug). Investments always resolve regardless.
A34: 9. Lifestyle Loan repayment defined | B34: +15%B now, -5%B at the start of each of the next 4 turns.
A36: Sheets | B36: Settings | Personalities | Balance_Audit | Actions_Master | Items_Mall | Investments | Jobs_Named | Jobs_Tiers | Pets | Audio_Music | Audio_SFX | Cards
A38: WHAT CHANGED IN v5
A39: 1. High IQ University rebuilt | B39: New Education_Paths sheet: 5 paths x 6 courses = 30 courses, with costs, click counts, strict unlock order, one-time completion, and job-tier gating. Replaces Take Class / Finish Undergrad / Master's / PhD, and fixes the bug where courses were unavailable.
A40: 2. Promotions removed | B40: New Job_Progression sheet. Ask for Promotion is deleted and there is no loyalty requirement. Tiers unlock on accumulated work clicks PLUS the matching education path.
A41: 3. Mall repriced to absolute dollars | B41: All 33 listed items set to the specified prices ($50 casual clothes ... $2000 car), 5-25x the v4 values.
A42: 4. Money economy rebuilt to match | B42: Job pay, rent, food, and the homeless cheque all rescaled. Without this the new prices would be unreachable: a $2000 car at the old $9 low wage was 222 work clicks.
A43: 5. Mall penalties removed | B43: Durag and Crocodile Sandals no longer carry stat penalties. No mall item has a penalty.
A44: 6. Flat trigger bonuses added | B44: 16 home items now grant fixed point bonuses when their trigger action happens at home (beds on sleep, bookshelf/plants/mirror/dining table/stove/hot tub on relax, desk/ergonomic chair on work-from-home, pet bed/pet toys on play, cold plunge on exercise, fridge/vacuum one-time on purchase).
A45: 7. Home fixtures exemption | B45: The best-item-per-slot rule no longer applies to home fixtures, so multiple owned fixtures each fire. Only one bed counts.
A46: 8. Fridge gating | B46: 2-week and 4-week groceries now require a fridge; a new 2-week option was added.
A47: OPEN DECISION | B47: Job click gates are absolute, so Short games realistically cannot reach High/Max tier. See the pacing warning in Job_Progression for Option A (keep) vs Option B (scale by mode).
A49: Sheets | B49: Settings | Personalities | Balance_Audit | Actions_Master | Items_Mall | Education_Paths | Job_Progression | Investments | Jobs_Named | Jobs_Tiers | Pets | Audio_Music | Audio_SFX | Cards
A51: WHAT CHANGED IN v6 (post-playtest)
A52: 1. Jobs re-ordered by tier | B52: Jobs_Named is now sorted Low -> Low+ -> Mid -> Mid+ -> High -> Max, then by building, with a Tier Rank column. It is no longer grouped by building. Twenty jobs were added to fill the empty Low+ and Mid+ rungs, and the stray "Max+" tier was normalised to Max.
A53: 2. Career growth slowed | B53: Career double-counting removed, tier values cut to 2/2/3/3/4/5, course Career gains halved, Update Resume Secretly cut from 5%B to 2%B and capped at once per turn, and a new per-turn diminishing-returns rule (100/50/25/10%) applied to every Career source. Maxing Career goes from under 4 turns to about 20. See the Career Patch v6 block in Settings.
A54: 3. Pay Rent rebuilt | B54: The Pay Rent rows now carry a full behavioural spec: always listed, never hidden, four display states, explicit success handler. The likely root cause is flagged: the Cost column is a multiple of B, so low rent is $100 and luxury rent $400, not $1 and $4.
A55: 4. Home comfort rebalanced | B55: Home exercise cut and capped at 2 per turn; gym actions buffed and given Connection; new Group Fitness Class action.
A56: 5. Order Fancy Food counts as eating | B56: New "Counts As (v6)" column on Actions_Master tags every action as Eat, Relax, Sleep, Work or Food supply, so hunger and stress clearing is data-driven instead of buried in prose.
A57: 6. Wages vary by building | B57: New Building_Map sheet. Pay = tier pay x Money Multiplier, rising with distance from the Corporate Soul Exchange: 1.00 at the hub, 1.10, 1.20, 1.35 at the edge, and 0.85 for Work From Home.
A58: 7. Luxury actions require purchases | B58: Sleep in Fancy Bed needs any bed, Take Luxury Bath needs the Hot Tub, Relax in Your Suite needs the Couch, Host Friends needs the new Fancy Dinnerware item (I042).
A59: 8. Chest Day reworked | B59: Flat Happiness +1 and Enlightenment -1 replace the old percentage Happiness penalty.
A60: 9. CPU difficulty added | B60: New CPU_Difficulty sheet: Easy / Medium / Hard, set globally or per bot, changing behaviour plus one clearly-labelled bot-only gain multiplier.
A61: 10. Turn limit is a setup value | B61: Turns per Game (10/15/20/30/50/Custom) added to Settings. The game ends at the selected round count or when a player maxes all four main stats, whichever comes first. The playtest build ended at 15 turns regardless — both likely causes are named in Settings.
A62: 11. Unit headers fixed | B62: Cost and Gain columns renamed from "%B" to "(xB)". A value of 1.0 means 100% of B, not 1%. This misreading is the most likely single cause of the rent bug and of wages that did not match the v5 wage table.
A63: 12. Work rows no longer pay | B63: Every Actions_Master "Work" row granted Money 6%B ($6) and Career on top of the job tier. Both are now zero; the job tier is the only source.
... A67: OPEN DECISION | B67: Job click gates (Option A absolute vs Option B scaled by mode) are still unresolved. With the v6 turn limit, Option B is now recommended: a 20-turn Short game cannot reach 110 work clicks, so under Option A the top half of the job ladder is visible but unreachable.

Sheet Settings
A1: Setting | B1: Value | C1: Notes
A2: Current Gain/Economy Base B | B2: 100 | C2: The number ALL percentages resolve against (gains, penalties, prices, rent, pay, card effects). Set to 100 / 250 / 350. This is NOT the stat cap.
A3: Short Game B (gain/economy base) | B3: 100 | C3: Short game economy base
A4: Medium Game B (gain/economy base) | B4: 250 | C4: Medium game economy base
A5: Long Game B (gain/economy base) | B5: 350 | C5: Long game economy base
A6: STAT CAPS T (endgame threshold — scale FASTER than B)
A7: Short Game T (stat cap) | B7: 100 | C7: Turn ratio T/B = 1.00 -> baseline length
A8: Medium Game T (stat cap) | B8: 500 | C8: Turn ratio T/B = 2.00 -> about twice as many turns as Short
A9: Long Game T (stat cap) | B9: 1000 | C9: Turn ratio T/B = 2.86 -> about 2.9x as many turns as Short
A10: Current Stat Cap T | B10: 100 | C10: Set to match the selected mode. Endgame triggers when a player hits T in all 4 main stats.
A11: Time Units per Turn | B11: 40 | C11: BUILD: 40 per turn (Game Setup offers 12-50). Sheet TU costs are used as authored. Per-turn rules written for a ~6 TU turn are much weaker at 40.
A12: Rent Interval (turns) | B12: 4 | C12: Rent-due overmap music also swaps in on these turns.
A13: Turn Timer Options (sec) | B13: 30 / 60 / 90 / 120 / Unlimited | C13: Chosen on Game Setup screen
A14: Max Players | B14: 4 | C14: 1 host + up to 3 joiners; CPU bots fill empty slots (min 2 total participants)
A16: Gain Tier | B16: % of B | C16: Meaning (resolves against B, NOT the stat cap)
A17: Tiny | B17: 0.025 | C17: Small action
A18: Standard | B18: 0.05 | C18: Normal action
A19: Strong | B19: 0.08 | C19: Good action
A20: Premium | B20: 0.12 | C20: Expensive/limited action
A21: Milestone | B21: 0.15 | C21: Degree/unlock/major action
A22: Major Milestone | B22: 0.2 | C22: Huge late-game action
A24: PERSONALITY MODIFIERS v2 (BALANCE PATCH)
A25: Stat | B25: Strength Bonus | C25: Weakness Penalty (v2) | D25: Max Final Multiplier | E25: Notes
A26: Connection | B26: 0.2 | C26: -0.1 | D26: 1.45 | E26: Main stat
A27: Health | B27: 0.2 | C27: -0.1 | D27: 1.45 | E27: Main stat
A28: Happiness | B28: 0.2 | C28: -0.1 | D28: 1.45 | E28: Main stat
A29: Career | B29: 0.1 | C29: -0.1 | D29: 1.25 | E29: Engine stat: weak strength (snowballs), full-size weakness
A30: Coolness Factor | B30: 0.15 | C30: -0.08 | D30: 1.35 | E30: Upkeep stat
A31: Critical Thinking | B31: 0.15 | C31: -0.08 | D31: 1.35 | E31: Upkeep stat
A32: Enlightenment | B32: 0.15 | C32: -0.08 | D32: 1.35 | E32: Upkeep stat
A33: Money | B33: 0.1 | C33: -0.08 | D33: 1.25 | E33: Engine stat: weak strength (snowballs), full-size weakness
A35: Final Gain Formula | B35: Base Gain x Personality Modifier x Pet Modifier x Best Item Modifier x Temporary Modifier, then clamp to the stat's Max Final Multiplier.
A36: Final Score Formula | B36: Connection + Health + Career + Happiness + AVG(Coolness, Critical Thinking, Enlightenment, Money) + AVG(Pet Happiness, Pet Health)
A38: UPKEEP TIME PENALTIES (locked in v3)
A39: Penalty | B39: Value | C39: Rule
A40: Hunger (forgot to eat last turn) | B40: -25% of the turn | C40: BUILD: 25% of next turn's Time Units (2026-07-20), not a flat -4.
A41: Stress (no relaxation for 2 turns) | B41: -15% of the turn | C41: BUILD: 15% of next turn's Time Units plus 5%B Health and 5%B Happiness.
A42: Stacking rule | B42: Both can apply | C42: Penalties stack (-6 total possible) but a turn never drops below 1 Time Unit.
A44: GAME LENGTH SCALING (fixed in v4)
A45: Problem in v3 | B45: Stat caps AND stat gains both scaled with T, so every action filled the same percentage of the bar in every mode (a 5% action needed ~20 uses in Short, Medium and Long alike). The modes only changed the size of the numbers, not the length of the game.
A46: Fix in v4 | B46: Two separate scalars. T = stat cap only. B = the base every percentage resolves against (gains, penalties, prices, rent, job pay, card effects). Because B grows more slowly than T, longer modes genuinely need more actions and more turns.
A47: Purchasing power | B47: Income and prices BOTH resolve against B, so purchasing power stays stable across modes. Prices are 2.5x Short in Medium and 3.5x Short in Long (not 5x/10x) — the ratio to wages is what matters, not the raw number.
A49: Mode | B49: Stat cap T | C49: Gain/economy base B | D49: Cap multiplier | E49: Gain multiplier | F49: Turn ratio (T/B) | G49: Max score
A50: Short | B50: 100 | C50: 100 | D50: 1.0x | E50: 1.00x | F50: 1.00x | G50: 600
A51: Medium | B51: 500 | C51: 250 | D51: 5.0x | E51: 2.50x | F51: 2.00x | G51: 3000
A52: Long | B52: 1000 | C52: 350 | D52: 10.0x | E52: 3.50x | F52: 2.86x | G52: 6000
A53: Worked example | B53: A Standard action is 5% of B. In Short it grants 5 points toward a cap of 100 (20 uses to max). In Medium it grants 12.5 points toward a cap of 500 (40 uses). In Long it grants 17.5 points toward a cap of 1000 (57 uses). That is the intended pacing difference.
A55: CARD EFFECT MODIFIER RULE (locked in v4)
A56: Rule | B56: Weekend Update card effects (status, investment, and event cards) are NOT modified by personality, pet, item, or temporary modifiers, and are NOT subject to the 1.25x income cap. Card values apply exactly as printed.
A57: Why | B57: Cards are already weighted by standing. Layering personality modifiers on top would double-dip: a Money-strength player in last place would get a standing bonus AND a personality bonus on the same payout, making rubber-banding unpredictable and very hard to balance. Modifiers still apply normally to all ACTION gains.
A58: Applies to losses too | B58: Card losses are also unmodified. A Money weakness does not deepen a RUG PULL, and a Money strength does not soften it.
A60: WEEKEND CARDS SETTING (three-way, fixed in v4)
A61: Mode | B61: Behaviour
A62: Full (default) | B62: Status cards + investment cards + event cards.
A63: Essential | B63: Status cards + investment cards only. Life-event cards are disabled. Purist mode: investments still pay out normally.
A64: Off (debug only) | B64: No cards shown. Status penalties AND investment returns still resolve silently and are written to the action log. Investments are never disabled — turning cards off must never change game outcomes, only presentation.
A66: MONEY ECONOMY REBUILD (v5)
A67: Why | B67: v5 sets mall prices as absolute dollar figures (casual clothes $50 ... car $2000). Those are 5-25x the old prices, so job pay, rent and food had to be rebuilt to match or the game would be unplayable. All dollar figures are SHORT-GAME (B=100) baselines and scale with B: Medium x2.5, Long x3.5.
A69: Income / cost | B69: Short $ | C69: %B | D69: Notes
A70: Work click — Low | B70: 40 | C70: 0.4 | D70: 2 Time Units per click
A71: Work click — Low+ | B71: 65 | C71: 0.65
A72: Work click — Mid | B72: 110 | C72: 1.1
A73: Work click — Mid+ | B73: 170 | C73: 1.7
A74: Work click — High | B74: 260 | C74: 2.6
A75: Work click — Max | B75: 400 | C75: 4
A76: Low-cost rent (every 4 turns) | B76: 100 | C76: 1 | D76: About 30% of a Low earner's 4-turn income; leaves room to save for education
A77: Luxury rent (every 4 turns) | B77: 400 | C77: 4 | D77: Requires Mid+ income to sustain
A78: Homeless Support Cheque | B78: 200 | C78: 2 | D78: Must cover casual clothes (50) + low rent (100) + a few meals
A79: Regret Burger meal | B79: 15 | C79: 0.15 | D79: Cheap food route
A80: Groceries — 1 week | B80: 40 | C80: 0.4 | D80: No fridge needed
A81: Groceries — 2 weeks | B81: 70 | C81: 0.7 | D81: REQUIRES FRIDGE
A82: Groceries — 4 weeks | B82: 130 | C82: 1.3 | D82: REQUIRES FRIDGE; best value
A83: Organic groceries — 1 week | B83: 70 | C83: 0.7 | D83: Better Health
A84: Education — Path 1 course | B84: 50 | C84: 0.5 | D84: x6 courses = 300
A85: Education — Path 2 course | B85: 100 | C85: 1 | D85: x6 = 600
A86: Education — Path 3 course | B86: 150 | C86: 1.5 | D86: x6 = 900
A87: Education — Path 4 course | B87: 200 | C87: 2 | D87: x6 = 1200
A88: Education — Path 5 course | B88: 250 | C88: 2.5 | D88: x6 = 1500; all five paths = 4500
A90: Career earnings check | B90: Working the canonical path to Max tier earns about $18,225 gross (10x40 + 15x65 + 20x110 + 25x170 + 40x260). Full education costs $4,500 and the complete mall catalogue is roughly $15,000, so no player can buy everything: the economy forces real choices.
A92: GAME LENGTH IN TURNS (new in v6) — THE TURN LIMIT IS A SETUP VALUE, NEVER A CONSTANT
A93: Turns per Game — options | B93: 10 / 15 / 20 / 30 / 50 / Custom | C93: Chosen on the Game Setup screen. Custom accepts 5-100.
A94: Default — Short | B94: 20 | C94: Suggested default; the player can change it.
A95: Default — Medium | B95: 40 | C95: Suggested default.
A96: Default — Long | B96: 60 | C96: Suggested default.
A97: A turn | B97: One ROUND | C97: One turn = one full round in which EVERY participant plays once. The turn counter increments when the round ends, not when a player ends their go.
A98: End condition A | B98: Turn limit reached | C98: The game ends when the selected number of ROUNDS has been completed.
A99: End condition B | B99: A player maxes all 4 main stats | C99: Finish the current round so everyone has had equal turns, then end.
A100: Which wins | B100: Whichever happens first | C100: Both conditions stay live for the whole game.
A101: HUD requirement | B101: Turn X of N | C101: The selected limit must be visible on screen every turn, and the last round must be announced as FINAL ROUND.
A102: BUG FIX v6 | B102: No hardcoded maximum | C102: The playtest build ended at 15 turns regardless of the value chosen at setup. Two known causes, check both: (1) a hardcoded constant such as MAX_TURNS = 15 in the turn loop; (2) the counter incrementing once per PLAYER turn instead of once per round, which ends a 4-player, 60-player-turn game after 15 rounds. Search the code for every literal 15 before shipping.
A104: CAREER PATCH v6 — CAREER WAS TOO EASY TO MAX
A105: Problem | B105: Career maxed in under 4 turns | C105: At Short, Update Resume Secretly cost 1 Time Unit and $0 and gave +5 Career, so six clicks a turn was +30 Career. Work clicks granted Career twice (once from the Actions_Master Work row, once from the job tier), and the 30 university courses added another 90 points against a cap of 100.
A106: Fix 1 — single source | B106: Job tier only | C106: Career from a work click comes from Jobs_Named / Job_Progression. The Actions_Master Work rows now grant 0 Career and 0 Money.
A107: Fix 2 — lower tier values | B107: 2 / 2 / 3 / 3 / 4 / 5 | C107: Career per click by tier, down from 3 / 5 / 7 / 10.
A108: Fix 3 — education halved | B108: 0.5 / 1 / 1.5 / 2 / 2.5 %B per course | C108: Path totals 3 / 6 / 9 / 12 / 15 = 45 points at Short, down from 90.
A109: Fix 4 — side actions cut | B109: Resume 2%B, Team Building 3%B, Get/Change Job 0 | C109: Update Resume Secretly and Attend Team Building Event are also limited to once per turn each.
A110: Fix 5 — diminishing returns | B110: 100% / 50% / 25% / 10% | C110: Within one turn, the 1st Career-granting action pays full, the 2nd half, the 3rd a quarter, the 4th and later a tenth. Round down, minimum 1 point. Applies to every Career source in the order taken. Career only — never Money, never other stats, never card effects.
A111: Result | B111: About 20 turns of focus to max Career | C111: Three Mid-tier work clicks now give 3 + 1.5 + 0.75 = 5 Career a turn instead of 18.
A112: Watch in playtest | B112: Career should be the slowest main stat | C112: If Career now feels impossible rather than merely expensive, raise the tier values before touching the diminishing-returns curve.
A114: BUILDING DISTANCE PAY (new in v6)
...

Sheet Personalities
A1: Type | B1: Main Strength | C1: Upkeep Strength | D1: Main Weakness | E1: Upkeep Weakness | F1: Notes
A2: ENFP | B2: Happiness | C2: Coolness Factor | D2: Health | E2: Money
A3: ESTP | B3: Health | C3: Money | D3: Happiness | E3: Enlightenment | F3: Engine type (Career or Money strength): lower net budget by design, offset by income/economic snowball
A4: ENTP | B4: Health | C4: Critical Thinking | D4: Connection | E4: Enlightenment
A5: ESFP | B5: Happiness | C5: Coolness Factor | D5: Career | E5: Critical Thinking
A6: ENFJ | B6: Connection | C6: Enlightenment | D6: Health | E6: Money
A7: ESFJ | B7: Connection | C7: Coolness Factor | D7: Health | E7: Critical Thinking
A8: ENTJ | B8: Career | C8: Money | D8: Happiness | E8: Coolness Factor | F8: Engine type (Career or Money strength): lower net budget by design, offset by income/economic snowball
A9: ESTJ | B9: Career | C9: Money | D9: Happiness | E9: Enlightenment | F9: Engine type (Career or Money strength): lower net budget by design, offset by income/economic snowball
A10: INTJ | B10: Career | C10: Critical Thinking | D10: Health | E10: Coolness Factor | F10: Engine type (Career or Money strength): lower net budget by design, offset by income/economic snowball
A11: ISTJ | B11: Career | C11: Money | D11: Connection | E11: Coolness Factor | F11: Engine type (Career or Money strength): lower net budget by design, offset by income/economic snowball
A12: ISFJ | B12: Connection | C12: Enlightenment | D12: Happiness | E12: Critical Thinking
A13: INFJ | B13: Connection | C13: Enlightenment | D13: Career | E13: Money
A14: INFP | B14: Happiness | C14: Enlightenment | D14: Career | E14: Money
A15: ISFP | B15: Happiness | C15: Coolness Factor | D15: Career | E15: Critical Thinking
A16: ISTP | B16: Health | C16: Critical Thinking | D16: Connection | E16: Enlightenment
A17: INTP | B17: Health | C17: Critical Thinking | D17: Connection | E17: Coolness Factor

Sheet Balance_Audit
A1: Why v2 exists: in v1, strength/weakness sizes varied so much per stat that net modifier budgets ranged from -2 (ENTJ/ESTJ/ISTJ) to +25 (INFJ/INFP), a 27-point spread. v2 unifies weakness penalties (main -10, upkeep -8), closing the spread to 15 points (+2 to +17). Career/Money-strength types remain intentionally lowest, offset by their income/job snowball rather than by stat-modifier perks.
A3: Type | B3: v1 Net Budget | C3: v2 Net Budget | D3: Change | E3: Notes
A4: ENFP | B4: 18 | C4: 17 | D4: =C4-B4
A5: ESTP | B5: 8 | C5: 12 | D5: =C5-B5 | E5: Engine type: lower budget by design, offset by income/job snowball
A6: ENTP | B6: 13 | C6: 17 | D6: =C6-B6
A7: ESFP | B7: 20 | C7: 17 | D7: =C7-B7
A8: ENFJ | B8: 18 | C8: 17 | D8: =C8-B8
A9: ESFJ | B9: 13 | C9: 17 | D9: =C9-B9
A10: ENTJ | B10: -2 | C10: 2 | D10: =C10-B10 | E10: Engine type: lower budget by design, offset by income/job snowball
A11: ESTJ | B11: -2 | C11: 2 | D11: =C11-B11 | E11: Engine type: lower budget by design, offset by income/job snowball
A12: INTJ | B12: 3 | C12: 7 | D12: =C12-B12 | E12: Engine type: lower budget by design, offset by income/job snowball
A13: ISTJ | B13: -2 | C13: 2 | D13: =C13-B13 | E13: Engine type: lower budget by design, offset by income/job snowball
A14: ISFJ | B14: 13 | C14: 17 | D14: =C14-B14
A15: INFJ | B15: 25 | C15: 17 | D15: =C15-B15
A16: INFP | B16: 25 | C16: 17 | D16: =C16-B16
A17: ISFP | B17: 20 | C17: 17 | D17: =C17-B17
A18: ISTP | B18: 13 | C18: 17 | D18: =C18-B18
A19: INTP | B19: 13 | C19: 17 | D19: =C19-B19
A21: v1 spread | B21: =MAX(B4:B19)-MIN(B4:B19) | C21: v2 spread | D21: =MAX(C4:C19)-MIN(C4:C19)
A23: Ongoing rule: log the winning personality in the debug panel every playtest. If any type's win rate leaves the 15-35 percent band (4-player expected = 25 percent) over 20+ games, adjust one weakness by 1-2 points and retest.

Sheet Building_Map
A1: BUILDING MAP AND DISTANCE PAY (new in v6). Wages are no longer identical everywhere. The Corporate Soul Exchange is the hub of the map and pays the baseline; the further a building sits from it, the higher its Money Multiplier, because getting there and back costs Time Units you could have spent working. The multiplier applies to MONEY ONLY — never to Career, never to stat gains, never to card effects. Pay per click = tier pay (Job_Progression) x building Money Multiplier, rounded to the nearest dollar. Display Name is the name shown in the build; if the build renames a building, record it here.
A3: Building (canonical) | B3: Display Name in build | C3: Ring (distance from Corporate) | D3: Travel Time Units from Corporate | E3: Money Multiplier (v6) | F3: Has jobs? | G3: Pay example — Mid tier ($110 base) | H3: Notes
A4: Corporate Soul Exchange | B4: Corporate Soul Exchange | C4: 1 | D4: 0 | E4: 1 | F4: Yes | G4: =ROUND(110*E4,0) | H4: The hub. Baseline pay. Also the job board: every job change happens here.
A5: Debtstreet Capital | B5: Debtstreet Capital | C5: 1 | D5: 1 | E5: 1 | F5: Yes | G5: =ROUND(110*E5,0) | H5: Across the plaza from Corporate. Baseline pay, but the investment desk is here.
A6: Mall | B6: Mall | C6: 1 | D6: 1 | E6: 1 | F6: Yes | G6: =ROUND(110*E6,0) | H6: Baseline pay. Compensated by being where every item is bought.
A7: Air One Supermarket | B7: Air One Supermarket | C7: 2 | D7: 1 | E7: 1.1 | F7: Yes | G7: =ROUND(110*E7,0) | H7: One ring out. Food route.
A8: High IQ University | B8: High IQ University | C8: 2 | D8: 1 | E8: 1.1 | F8: Yes | G8: =ROUND(110*E8,0) | H8: One ring out. Education route.
A9: Regret Burger | B9: Regret Burger | C9: 2 | D9: 1 | E9: 1.1 | F9: Yes | G9: =ROUND(110*E9,0) | H9: One ring out. Cheap food route.
A10: Low Cost Housing | B10: Low Cost Housing | C10: 2 | D10: 1 | E10: 1 | F10: No | G10: — | H10: Starting home. No jobs. Work From Home uses the 0.85 convenience multiplier (see below).
A11: Bro Science Gym | B11: Bro Science Gym | C11: 3 | D11: 2 | E11: 1.2 | F11: Yes | G11: =ROUND(110*E11,0) | H11: Two rings out. Health and Connection route.
A12: Bad Decisions Club | B12: Bad Decisions Club | C12: 3 | D12: 2 | E12: 1.2 | F12: Yes | G12: =ROUND(110*E12,0) | H12: Two rings out. Night-side of the map.
A13: Ethical Pet Shop | B13: Ethical Pet Shop | C13: 3 | D13: 2 | E13: 1.2 | F13: Yes | G13: =ROUND(110*E13,0) | H13: Two rings out. Pet route.
A14: Luxury Apartments | B14: Heelton Heights (CONFIRM) | C14: 3 | D14: 2 | E14: 1 | F14: No | G14: — | H14: Premium home. No jobs. Work From Home uses the 0.85 convenience multiplier (see below). The playtest build calls this building Heelton Heights — confirm the mapping before shipping.
A15: Park | B15: Park | C15: 3 | D15: 2 | E15: 1 | F15: No | G15: — | H15: Recovery / homeless fallback. No jobs.
A16: Emotional Baggage Airport | B16: Emotional Baggage Airport | C16: 4 | D16: 3 | E16: 1.35 | F16: Yes | G16: =ROUND(110*E16,0) | H16: Edge of the map. Highest wage multiplier in the game — worth the trip if you are already flying.
A17: Re-Education Temple | B17: Re-Education Temple | C17: 4 | D17: 3 | E17: 1.35 | F17: Yes | G17: =ROUND(110*E17,0) | H17: Edge of the map. Highest wage multiplier in the game.
A19: RULES
A20: Money only | B20: The Money Multiplier applies ONLY to Money earned from a Work click (and Work From Home). It never touches Career gain, stat gains, card effects, or investment returns.
A21: Work From Home | B21: Work From Home at either housing building uses a Money Multiplier of 0.85. Working in your pyjamas costs no travel, so it must pay less than going in. It still counts as a work click for tier progression and still uses your current job tier.
A22: Travel is the cost | B22: Ring 3 and Ring 4 buildings must genuinely cost 2 and 3 Time Units to reach from the hub. If travel is free, the multiplier is a straight buff and the trade-off disappears.
A23: Rounding | B23: Pay per click = ROUND(tier pay x multiplier, 0). At Short a Mid click is $110 at Corporate, $121 at Air One, $132 at the Gym, $149 at the Airport.
A24: Scaling | B24: Multipliers do not change with game length. Tier pay already scales with B (Medium x2.5, Long x3.5).
A25: Ring numbers are a starting point | B25: Ring assignments here describe the intended map layout, not measured coordinates. If the built map places a building differently, update this sheet to match the map rather than moving the building.

Sheet CPU_Difficulty
A1: CPU DIFFICULTY (new in v6). Difficulty is chosen on the Game Setup screen and can be set per bot or globally for all bots. Default is Medium. Difficulty changes ONLY how bots behave and one explicitly-labelled bot-only gain multiplier. It never changes the rules, the prices, the card deck, or anything a human player experiences.
A3: Behaviour | B3: Easy | C3: Medium | D3: Hard
A4: Action choice | B4: Picks at random from the affordable actions in the building it is standing in. | C4: Scores every affordable action and picks randomly from the top 3. | D4: Scores every affordable action and always picks the best.
A5: Planning horizon | B5: One action at a time. No saving up. | C5: Plans the current turn. Will save money across 2-3 turns for a named goal. | D5: Plans several turns ahead. Saves for education paths, job tiers, and housing deliberately.
A6: Forgets to eat | B6: 40% of turns | C6: 15% of turns | D6: Never
A7: Forgets to relax | B7: 40% of stress checks | C7: 15% of stress checks | D7: Never
A8: Pays rent | B8: Only if it happens to be in the building on the due turn (often goes homeless). | C8: Pays on the due turn if it can afford it. | D8: Pre-pays and keeps a rent reserve; never goes homeless voluntarily.
A9: Education | B9: Ignores High IQ University. | C9: Completes Path 1 and Path 2 if the game runs long enough. | D9: Treats education as a priority and pushes as far up the paths as the turn count allows.
A10: Job tiers | B10: Takes whatever job it qualifies for by accident. | C10: Works toward the next tier once it is one gate away. | D10: Works the highest-paying eligible job and targets the next tier from turn 1.
A11: Travel for wages | B11: Never travels for pay; works wherever it is. | C11: Uses a nearby building. | D11: Uses the Money Multiplier: travels to a far building when it plans 2+ work clicks.
A12: Investments | B12: Does not invest. | C12: Buys Savings and Bonds only. | D12: Standing-aware: crypto when last, bonds and savings when leading, cashes out before taking the lead.
A13: Mall shopping | B13: Buys impulsively, often unaffordable-adjacent junk. | C13: Buys job-required clothing and one or two home fixtures. | D13: Buys job-required clothing first, then the highest value-per-dollar fixtures.
A14: Pet care | B14: Frequently misses feedings; may let the pet die. | C14: Feeds on the warning card. | D14: Never misses a feeding.
A15: Bot-only gain multiplier | B15: 0.85x | C15: 1.00x | D15: 1.10x
A17: Bot-only multiplier scope | B17: The 0.85x / 1.00x / 1.10x multiplier applies to a BOT's stat and money gains from ACTIONS only. It is never applied to a human player, never to card effects, and never to investment returns. Show it in the debug panel so balance tests can be run with it switched off.
A18: Per-bot or global | B18: Game Setup offers one difficulty control for all bots plus an expandable per-bot override, so a player can face one Hard bot and two Easy bots.
A19: Skipping unchanged | B19: Skip CPU Turns works identically at every difficulty. A Hard bot must not take longer in real time.
A20: Default | B20: Medium.

Sheet Actions_Master
A1: Action_ID | B1: Building | C1: Action | D1: Category | E1: Requirement / Condition | F1: Time Units | G1: Cost (xB) — 1.0 = 100% of B | H1: Cost Short | I1: Cost Medium | J1: Cost Long | K1: Gain Stat 1 | L1: Gain (xB) 1 — 1.0 = 100% of B | M1: Gain Short | N1: Gain Medium | O1: Gain Long | P1: Gain Stat 2 | Q1: Gain (xB) 2 — 1.0 = 100% of B | R1: Gain2 Short | S1: Gain2 Medium | T1: Gain2 Long | U1: Pet Gain | V1: Pet (xB) | W1: Penalty Stat 1 | X1: Penalty (xB) 1 | Y1: Penalty Stat 2 | Z1: Penalty (xB) 2 | AA1: Unlock / Effect | AB1: Balance Notes | AC1: MVP Priority | AD1: Counts As (v6) | AE1: Requires Item (v6) | AF1: Per-Turn Limit (v6) | AG1: Flat Bonus (v6) | AH1: Money Multiplier (v6) | AI1: v6 Change
A2: A001 | B2: Low Cost Housing | C2: Sleep in Bunk Bed | D2: Rest | E2: Must be housed here | F2: 2 | G2: 0 | H2: =ROUND($G2*Settings!$B$3,0) | I2: =ROUND($G2*Settings!$B$4,0) | J2: =ROUND($G2*Settings!$B$5,0) | K2: Health | L2: 0.05 | M2: =ROUND($L2*Settings!$B$3,0) | N2: =ROUND($L2*Settings!$B$4,0) | O2: =ROUND($L2*Settings!$B$5,0) | Q2: 0 | R2: =ROUND($Q2*Settings!$B$3,0) | S2: =ROUND($Q2*Settings!$B$4,0) | T2: =ROUND($Q2*Settings!$B$5,0) | V2: 0 | Z2: 0 | AA2: Reduces stress; ends hunger penalty timer if food was eaten | AB2: Safe recovery, not a winning engine | AC2: MVP | AD2: Sleep + Relax
A3: A002 | B3: Low Cost Housing | C3: Relax in Your Room | D3: Relax | E3: Must be housed here | F3: 1 | G3: 0 | H3: =ROUND($G3*Settings!$B$3,0) | I3: =ROUND($G3*Settings!$B$4,0) | J3: =ROUND($G3*Settings!$B$5,0) | K3: Happiness | L3: 0.04 | M3: =ROUND($L3*Settings!$B$3,0) | N3: =ROUND($L3*Settings!$B$4,0) | O3: =ROUND($L3*Settings!$B$5,0) | Q3: 0 | R3: =ROUND($Q3*Settings!$B$3,0) | S3: =ROUND($Q3*Settings!$B$4,0) | T3: =ROUND($Q3*Settings!$B$5,0) | V3: 0 | Z3: 0 | AA3: Counts as relaxing for 2-turn stress rule | AB3: Cheap stress management | AC3: MVP | AD3: Relax
A4: A003 | B4: Low Cost Housing | C4: Take Communal Shower | D4: Health | E4: Must be housed here | F4: 1 | G4: 0 | H4: =ROUND($G4*Settings!$B$3,0) | I4: =ROUND($G4*Settings!$B$4,0) | J4: =ROUND($G4*Settings!$B$5,0) | K4: Health | L4: 0.025 | M4: =ROUND($L4*Settings!$B$3,0) | N4: =ROUND($L4*Settings!$B$4,0) | O4: =ROUND($L4*Settings!$B$5,0) | Q4: 0 | R4: =ROUND($Q4*Settings!$B$3,0) | S4: =ROUND($Q4*Settings!$B$4,0) | T4: =ROUND($Q4*Settings!$B$5,0) | V4: 0 | Z4: 0 | AB4: Small maintenance action | AC4: MVP
A5: A004 | B5: Low Cost Housing | C5: Exercise in Former Yard | D5: Health | E5: Must be housed here | F5: 1 | G5: 0 | H5: =ROUND($G5*Settings!$B$3,0) | I5: =ROUND($G5*Settings!$B$4,0) | J5: =ROUND($G5*Settings!$B$5,0) | K5: Health | L5: 0.025 | M5: =ROUND($L5*Settings!$B$3,0) | N5: =ROUND($L5*Settings!$B$4,0) | O5: =ROUND($L5*Settings!$B$5,0) | Q5: 0 | R5: =ROUND($Q5*Settings!$B$3,0) | S5: =ROUND($Q5*Settings!$B$4,0) | T5: =ROUND($Q5*Settings!$B$5,0) | V5: 0 | W5: Happiness | X5: 0.01 | Z5: 0 | AB5: v6: Health cut from 4%B to 2.5%B and limited to 2 per turn. Free, zero-travel exercise was out-earning the gym. | AC5: MVP | AF5: 2 per turn | AI5: Health 0.04 -> 0.025; max 2 per turn
A6: A005 | B6: Low Cost Housing | C6: Decorate Your Cell | D6: Home | E6: Furniture owned | F6: 1 | G6: 0 | H6: =ROUND($G6*Settings!$B$3,0) | I6: =ROUND($G6*Settings!$B$4,0) | J6: =ROUND($G6*Settings!$B$5,0) | K6: Happiness | L6: 0.05 | M6: =ROUND($L6*Settings!$B$3,0) | N6: =ROUND($L6*Settings!$B$4,0) | O6: =ROUND($L6*Settings!$B$5,0) | Q6: 0 | R6: =ROUND($Q6*Settings!$B$3,0) | S6: =ROUND($Q6*Settings!$B$4,0) | T6: =ROUND($Q6*Settings!$B$5,0) | V6: 0 | Z6: 0 | AA6: Uses owned furniture bonus | AB6: Requires prior Mall spending | AC6: MVP
A7: A006 | B7: Low Cost Housing | C7: Hang With Pet | D7: Pet | E7: Own a pet | F7: 1 | G7: 0 | H7: =ROUND($G7*Settings!$B$3,0) | I7: =ROUND($G7*Settings!$B$4,0) | J7: =ROUND($G7*Settings!$B$5,0) | K7: Connection | L7: 0.025 | M7: =ROUND($L7*Settings!$B$3,0) | N7: =ROUND($L7*Settings!$B$4,0) | O7: =ROUND($L7*Settings!$B$5,0) | Q7: 0 | R7: =ROUND($Q7*Settings!$B$3,0) | S7: =ROUND($Q7*Settings!$B$4,0) | T7: =ROUND($Q7*Settings!$B$5,0) | U7: Pet Happiness | V7: 0.05 | Z7: 0 | AB7: Pet route support | AC7: MVP
A8: A007 | B8: Low Cost Housing | C8: Feed Pet | D8: Pet | E8: Own pet + pet food | F8: 1 | G8: 0 | H8: =ROUND($G8*Settings!$B$3,0) | I8: =ROUND($G8*Settings!$B$4,0) | J8: =ROUND($G8*Settings!$B$5,0) | L8: 0 | M8: =ROUND($L8*Settings!$B$3,0) | N8: =ROUND($L8*Settings!$B$4,0) | O8: =ROUND($L8*Settings!$B$5,0) | Q8: 0 | R8: =ROUND($Q8*Settings!$B$3,0) | S8: =ROUND($Q8*Settings!$B$4,0) | T8: =ROUND($Q8*Settings!$B$5,0) | U8: Pet Health | V8: 0.08 | Z8: 0 | AA8: Prevents pet warning/death spiral | AB8: Pet maintenance | AC8: MVP
A9: A008 | B9: Low Cost Housing | C9: Pay Low-Cost Rent | D9: Rent | E9: Always available while housed here | F9: 0 | G9: 1 | H9: =ROUND($G9*Settings!$B$3,0) | I9: =ROUND($G9*Settings!$B$4,0) | J9: =ROUND($G9*Settings!$B$5,0) | L9: 0 | M9: =ROUND($L9*Settings!$B$3,0) | N9: =ROUND($L9*Settings!$B$4,0) | O9: =ROUND($L9*Settings!$B$5,0) | Q9: 0 | R9: =ROUND($Q9*Settings!$B$3,0) | S9: =ROUND($Q9*Settings!$B$4,0) | T9: =ROUND($Q9*Settings!$B$5,0) | V9: 0 | Z9: 0 | AA9: PAY RENT. This action is ALWAYS listed in the housing menu and is never hidden, never filtered out, and never costs Time Units. It has four display states: RENT DUE (shows the amount, highlighted), PAID (shows the turn the next payment falls due), NOT YET DUE (shows turns remaining; the player may pre-pay the next cycle), and CANNOT AFFORD (greyed, shows the exact shortfall). On success: deduct the money, play PP-Money.mp3, write a log line, and set the next due turn to the current turn + the Rent Interval. If rent is still unpaid when the rent-due turn ends, the player becomes homeless. | AB9: v6 BUG FIX. Cost is a MULTIPLE of B, not a percent: 1 = $100 low rent, 4 = $400 luxury rent at the Short baseline. Reading these as 1% and 4% of B charges $1 and $4 and breaks the economy. A menu row that does nothing when clicked is the reported playtest bug. | AC9: MVP | AI9: Pay Rent rebuilt: always visible, four states, explicit handler
A10: A009 | B10: Luxury Apartments | C10: Sleep in Fancy Bed | D10: Rest | E10: Luxury apartment + any bed owned | F10: 2 | G10: 0 | H10: =ROUND($G10*Settings!$B$3,0) | I10: =ROUND($G10*Settings!$B$4,0) | J10: =ROUND($G10*Settings!$B$5,0) | K10: Health | L10: 0.08 | M10: =ROUND($L10*Settings!$B$3,0) | N10: =ROUND($L10*Settings!$B$4,0) | O10: =ROUND($L10*Settings!$B$5,0) | Q10: 0 | R10: =ROUND($Q10*Settings!$B$3,0) | S10: =ROUND($Q10*Settings!$B$4,0) | T10: =ROUND($Q10*Settings!$B$5,0) | V10: 0 | Z10: 0 | AA10: Reduces stress strongly | AB10: Premium housing advantage | AC10: MVP | AD10: Sleep + Relax | AE10: Any bed owned (Lumpy, Nice or Premium) | AI10: Now requires a bed purchase
A11: A010 | B11: Luxury Apartments | C11: Take Luxury Bath | D11: Relax | E11: Luxury apartment + Hot Tub owned | F11: 1 | G11: 0.2 | H11: =ROUND($G11*Settings!$B$3,0) | I11: =ROUND($G11*Settings!$B$4,0) | J11: =ROUND($G11*Settings!$B$5,0) | K11: Health | L11: 0.04 | M11: =ROUND($L11*Settings!$B$3,0) | N11: =ROUND($L11*Settings!$B$4,0) | O11: =ROUND($L11*Settings!$B$5,0) | P11: Happiness | Q11: 0.04 | R11: =ROUND($Q11*Settings!$B$3,0) | S11: =ROUND($Q11*Settings!$B$4,0) | T11: =ROUND($Q11*Settings!$B$5,0) | V11: 0 | Z11: 0 | AA11: Counts as relaxing | AB11: Small paid luxury action | v6.1: restored the v5.1 price that matches the painted menu ($20). | AC11: MVP | AD11: Relax | AE11: Hot Tub | AI11: Now requires a Hot Tub purchase
A12: A011 | B12: Luxury Apartments | C12: Relax in Your Suite | D12: Relax | E12: Luxury apartment + Couch owned | F12: 1 | G12: 0 | H12: =ROUND($G12*Settings!$B$3,0) | I12: =ROUND($G12*Settings!$B$4,0) | J12: =ROUND($G12*Settings!$B$5,0) | K12: Happiness | L12: 0.08 | M12: =ROUND($L12*Settings!$B$3,0) | N12: =ROUND($L12*Settings!$B$4,0) | O12: =ROUND($L12*Settings!$B$5,0) | Q12: 0 | R12: =ROUND($Q12*Settings!$B$3,0) | S12: =ROUND($Q12*Settings!$B$4,0) | T12: =ROUND($Q12*Settings!$B$5,0) | V12: 0 | Z12: 0 | AA12: Counts as relaxing | AB12: Strong happiness route | AC12: MVP | AD12: Relax | AE12: Any couch owned | AI12: Now requires a Couch purchase
A13: A012 | B13: Luxury Apartments | C13: Exercise in Condo Gym | D13: Health | E13: Luxury apartment | F13: 1 | G13: 0 | H13: =ROUND($G13*Settings!$B$3,0) | I13: =ROUND($G13*Settings!$B$4,0) | J13: =ROUND($G13*Settings!$B$5,0) | K13: Health | L13: 0.03 | M13: =ROUND($L13*Settings!$B$3,0) | N13: =ROUND($L13*Settings!$B$4,0) | O13: =ROUND($L13*Settings!$B$5,0) | Q13: 0 | R13: =ROUND($Q13*Settings!$B$3,0) | S13: =ROUND($Q13*Settings!$B$4,0) | T13: =ROUND($Q13*Settings!$B$5,0) | V13: 0 | Z13: 0 | AB13: v6: Health cut from 6%B to 3%B and limited to 2 per turn. This was the best Health-per-Time-Unit action in the game, it was free, and it cost no travel. | AC13: MVP | AF13: 2 per turn | AI13: Health 0.06 -> 0.03; max 2 per turn
A14: A013 | B14: Luxury Apartments | C14: Order Fancy Food | D14: Food | E14: Luxury apartment | F14: 1 | G14: 0.8 | H14: =ROUND($G14*Settings!$B$3,0) | I14: =ROUND($G14*Settings!$B$4,0) | J14: =ROUND($G14*Settings!$B$5,0) | K14: Happiness | L14: 0.06 | M14: =ROUND($L14*Settings!$B$3,0) | N14: =ROUND($L14*Settings!$B$4,0) | O14: =ROUND($L14*Settings!$B$5,0) | Q14: 0 | R14: =ROUND($Q14*Settings!$B$3,0) | S14: =ROUND($Q14*Settings!$B$4,0) | T14: =ROUND($Q14*Settings!$B$5,0) | V14: 0 | Z14: 0 | AA14: COUNTS AS EATING. Clears this turn's hunger requirement exactly like a Regret Burger meal or a grocery meal, and prevents the YOU FORGOT TO EAT! card next turn. | AB14: Expensive convenience | v6.1: restored the v5.1 price that matches the painted menu ($80). | AC14: MVP | AD14: Eat | AI14: Now explicitly counts as eating (Counts As = Eat)
A15: A014 | B15: Luxury Apartments | C15: Host Friends | D15: Social | E15: Luxury apartment + Fancy Dinnerware owned | F15: 2 | G15: 0.6 | H15: =ROUND($G15*Settings!$B$3,0) | I15: =ROUND($G15*Settings!$B$4,0) | J15: =ROUND($G15*Settings!$B$5,0) | K15: Connection | L15: 0.08 | M15: =ROUND($L15*Settings!$B$3,0) | N15: =ROUND($L15*Settings!$B$4,0) | O15: =ROUND($L15*Settings!$B$5,0) | P15: Coolness Factor | Q15: 0.04 | R15: =ROUND($Q15*Settings!$B$3,0) | S15: =ROUND($Q15*Settings!$B$4,0) | T15: =ROUND($Q15*Settings!$B$5,0) | V15: 0 | Z15: 0 | AB15: Luxury social route | v6.1: restored the v5.1 price that matches the painted menu ($60). | AC15: MVP | AE15: Fancy Dinnerware | AI15: Now requires Fancy Dinnerware (new item I042)
A16: A015 | B16: Luxury Apartments | C16: Work From Home | D16: Work | E16: Luxury apartment + computer + desk + job | F16: 2 | G16: 0 | H16: =ROUND($G16*Settings!$B$3,0) | I16: =ROUND($G16*Settings!$B$4,0) | J16: =ROUND($G16*Settings!$B$5,0) | K16: From job tier | L16: 0 | M16: =ROUND($L16*Settings!$B$3,0) | N16: =ROUND($L16*Settings!$B$4,0) | O16: =ROUND($L16*Settings!$B$5,0) | P16: From job tier | Q16: 0 | R16: =ROUND($Q16*Settings!$B$3,0) | S16: =ROUND($Q16*Settings!$B$4,0) | T16: =ROUND($Q16*Settings!$B$5,0) | V16: 0 | W16: Health | X16: 0.025 | Y16: Happiness | Z16: 0.025 | AA16: Counts as a Work click for tier progression. Money and Career come from the current job tier (Jobs_Named / Job_Progression), multiplied by 0.85 because working from home costs no travel. | AB16: Good but still has burnout | AC16: MVP | AD16: Work | AH16: 0.85 | AI16: Money/Career now come from job tier; 0.85 convenience multiplier
A17: A016 | B17: Luxury Apartments | C17: Pet Spa Treatment | D17: Pet | E17: Luxury apartment + own pet | F17: 1 | G17: 0.8 | H17: =ROUND($G17*Settings!$B$3,0) | I17: =ROUND($G17*Settings!$B$4,0) | J17: =ROUND($G17*Settings!$B$5,0) | L17: 0 | M17: =ROUND($L17*Settings!$B$3,0) | N17: =ROUND($L17*Settings!$B$4,0) | O17: =ROUND($L17*Settings!$B$5,0) | Q17: 0 | R17: =ROUND($Q17*Settings!$B$3,0) | S17: =ROUND($Q17*Settings!$B$4,0) | T17: =ROUND($Q17*Settings!$B$5,0) | U17: Pet Health | V17: 0.1 | Z17: 0 | AB17: Premium pet recovery | v6.1: restored the v5.1 price that matches the painted menu ($80). | AC17: MVP
A18: A017 | B18: Luxury Apartments | C18: Pay Luxury Rent | D18: Rent | E18: Always available while housed here | F18: 0 | G18: 4 | H18: =ROUND($G18*Settings!$B$3,0) | I18: =ROUND($G18*Settings!$B$4,0) | J18: =ROUND($G18*Settings!$B$5,0) | L18: 0 | M18: =ROUND($L18*Settings!$B$3,0) | N18: =ROUND($L18*Settings!$B$4,0) | O18: =ROUND($L18*Settings!$B$5,0) | Q18: 0 | R18: =ROUND($Q18*Settings!$B$3,0) | S18: =ROUND($Q18*Settings!$B$4,0) | T18: =ROUND($Q18*Settings!$B$5,0) | V18: 0 | Z18: 0 | AA18: PAY RENT. This action is ALWAYS listed in the housing menu and is never hidden, never filtered out, and never costs Time Units. It has four display states: RENT DUE (shows the amount, highlighted), PAID (shows the turn the next payment falls due), NOT YET DUE (shows turns remaining; the player may pre-pay the next cycle), and CANNOT AFFORD (greyed, shows the exact shortfall). On success: deduct the money, play PP-Money.mp3, write a log line, and set the next due turn to the current turn + the Rent Interval. If rent is still unpaid when the rent-due turn ends, the player becomes homeless. | AB18: v6 BUG FIX. Cost is a MULTIPLE of B, not a percent: 1 = $100 low rent, 4 = $400 luxury rent at the Short baseline. Reading these as 1% and 4% of B charges $1 and $4 and breaks the economy. A menu row that does nothing when clicked is the reported playtest bug. | AC18: MVP | AI18: Pay Rent rebuilt: always visible, four states, explicit handler
A19: A018 | B19: Park | C19: Take a Walk | D19: Health | E19: None | F19: 1 | G19: 0 | H19: =ROUND($G19*Settings!$B$3,0) | I19: =ROUND($G19*Settings!$B$4,0) | J19: =ROUND($G19*Settings!$B$5,0) | K19: Health | L19: 0.025 | M19: =ROUND($L19*Settings!$B$3,0) | N19: =ROUND($L19*Settings!$B$4,0) | O19: =ROUND($L19*Settings!$B$5,0) | P19: Happiness | Q19: 0.025 | R19: =ROUND($Q19*Settings!$B$3,0) | S19: =ROUND($Q19*Settings!$B$4,0) | T19: =ROUND($Q19*Settings!$B$5,0) | V19: 0 | Z19: 0 | AB19: Small free action | AC19: MVP
A20: A019 | B20: Park | C20: Touch Grass | D20: Enlightenment | E20: None | F20: 1 | G20: 0 | H20: =ROUND($G20*Settings!$B$3,0) | I20: =ROUND($G20*Settings!$B$4,0) | J20: =ROUND($G20*Settings!$B$5,0) | K20: Enlightenment | L20: 0.05 | M20: =ROUND($L20*Settings!$B$3,0) | N20: =ROUND($L20*Settings!$B$4,0) | O20: =ROUND($L20*Settings!$B$5,0) | P20: Health | Q20: 0.025 | R20: =ROUND($Q20*Settings!$B$3,0) | S20: =ROUND($Q20*Settings!$B$4,0) | T20: =ROUND($Q20*Settings!$B$5,0) | V20: 0 | Z20: 0 | AB20: Free enlightenment route | AC20: MVP
A21: A020 | B21: Park | C21: Feed Judgmental Ducks | D21: Fun | E21: None | F21: 1 | G21: 0.01 | H21: =ROUND($G21*Settings!$B$3,0) | I21: =ROUND($G21*Settings!$B$4,0) | J21: =ROUND($G21*Settings!$B$5,0) | K21: Happiness | L21: 0.04 | M21: =ROUND($L21*Settings!$B$3,0) | N21: =ROUND($L21*Settings!$B$4,0) | O21: =ROUND($L21*Settings!$B$5,0) | Q21: 0 | R21: =ROUND($Q21*Settings!$B$3,0) | S21: =ROUND($Q21*Settings!$B$4,0) | T21: =ROUND($Q21*Settings!$B$5,0) | V21: 0 | Z21: 0 | AB21: Cheap happiness | AC21: MVP
A22: A021 | B22: Park | C22: Use Restroom of Uncertainty | D22: Health | E22: None | F22: 1 | G22: 0 | H22: =ROUND($G22*Settings!$B$3,0) | I22: =ROUND($G22*Settings!$B$4,0) | J22: =ROUND($G22*Settings!$B$5,0) | K22: Health | L22: 0.02 | M22: =ROUND($L22*Settings!$B$3,0) | N22: =ROUND($L22*Settings!$B$4,0) | O22: =ROUND($L22*Settings!$B$5,0) | Q22: 0 | R22: =ROUND($Q22*Settings!$B$3,0) | S22: =ROUND($Q22*Settings!$B$4,0) | T22: =ROUND($Q22*Settings!$B$5,0) | V22: 0 | W22: Happiness | X22: 0.01 | Z22: 0 | AB22: Comedy maintenance | AC22: MVP
A23: A022 | B23: Park | C23: Nap on Park Bench | D23: Rest | E23: None | F23: 1 | G23: 0 | H23: =ROUND($G23*Settings!$B$3,0) | I23: =ROUND($G23*Settings!$B$4,0) | J23: =ROUND($G23*Settings!$B$5,0) | K23: Health | L23: 0.03 | M23: =ROUND($L23*Settings!$B$3,0) | N23: =ROUND($L23*Settings!$B$4,0) | O23: =ROUND($L23*Settings!$B$5,0) | P23: Happiness | Q23: 0.02 | R23: =ROUND($Q23*Settings!$B$3,0) | S23: =ROUND($Q23*Settings!$B$4,0) | T23: =ROUND($Q23*Settings!$B$5,0) | V23: 0 | Z23: 0 | AA23: Counts as relaxing | AB23: Free stress recovery | AC23: MVP | AD23: Relax
A24: A023 | B24: Park | C24: Pick Up Loose Change | D24: Money | E24: None | F24: 1 | G24: 0 | H24: =ROUND($G24*Settings!$B$3,0) | I24: =ROUND($G24*Settings!$B$4,0) | J24: =ROUND($G24*Settings!$B$5,0) | K24: Money | L24: 0.025 | M24: =ROUND($L24*Settings!$B$3,0) | N24: =ROUND($L24*Settings!$B$4,0) | O24: =ROUND($L24*Settings!$B$5,0) | Q24: 0 | R24: =ROUND($Q24*Settings!$B$3,0) | S24: =ROUND($Q24*Settings!$B$4,0) | T24: =ROUND($Q24*Settings!$B$5,0) | V24: 0 | Z24: 0 | AB24: Tiny money route | AC24: MVP
A25: A024 | B25: Park | C25: Homeless Support Cheque | D25: Comeback | E25: Homeless + rent cycle only | F25: 0 | G25: 0 | H25: =ROUND($G25*Settings!$B$3,0) | I25: =ROUND($G25*Settings!$B$4,0) | J25: =ROUND($G25*Settings!$B$5,0) | K25: Money | L25: 2 | M25: =ROUND($L25*Settings!$B$3,0) | N25: =ROUND($L25*Settings!$B$4,0) | O25: =ROUND($L25*Settings!$B$5,0) | Q25: 0 | R25: =ROUND($Q25*Settings!$B$3,0) | S25: =ROUND($Q25*Settings!$B$4,0) | T25: =ROUND($Q25*Settings!$B$5,0) | V25: 0 | Z25: 0 | AA25: Enough for casual clothes + low-cost rent | AB25: v5: cheque raised to $200 so it still covers casual clothes ($50) + low rent ($100) + a few meals. | AC25: MVP
A26: A025 | B26: Park | C26: Sleep in Park if Homeless | D26: Homeless | E26: Homeless | F26: 2 | G26: 0 | H26: =ROUND($G26*Settings!$B$3,0) | I26: =ROUND($G26*Settings!$B$4,0) | J26: =ROUND($G26*Settings!$B$5,0) | K26: Health | L26: 0.015 | M26: =ROUND($L26*Settings!$B$3,0) | N26: =ROUND($L26*Settings!$B$4,0) | O26: =ROUND($L26*Settings!$B$5,0) | Q26: 0 | R26: =ROUND($Q26*Settings!$B$3,0) | S26: =ROUND($Q26*Settings!$B$4,0) | T26: =ROUND($Q26*Settings!$B$5,0) | V26: 0 | W26: Happiness | X26: 0.08 | Y26: Health | Z26: 0.03 | AA26: Survive turn | AB26: Painful but recoverable | AC26: MVP | AD26: Sleep + Relax
A27: A026 | B27: Air One Supermarket | C27: Buy 1 Week of Groceries | D27: Food | E27: None | F27: 1 | G27: 0.4 | H27: =ROUND($G27*Settings!$B$3,0) | I27: =ROUND($G27*Settings!$B$4,0) | J27: =ROUND($G27*Settings!$B$5,0) | K27: Health | L27: 0.04 | M27: =ROUND($L27*Settings!$B$3,0) | N27: =ROUND($L27*Settings!$B$4,0) | O27: =ROUND($L27*Settings!$B$5,0) | Q27: 0 | R27: =ROUND($Q27*Settings!$B$3,0) | S27: =ROUND($Q27*Settings!$B$4,0) | T27: =ROUND($Q27*Settings!$B$5,0) | V27: 0 | Z27: 0 | AA27: Adds 1 week food supply | AB27: v5: 1 week groceries $40 | AC27: MVP | AD27: Food supply (not a meal)
A28: A027 | B28: Air One Supermarket | C28: Buy 1 Week of Organic Groceries | D28: Food | E28: None | F28: 1 | G28: 0.7 | H28: =ROUND($G28*Settings!$B$3,0) | I28: =ROUND($G28*Settings!$B$4,0) | J28: =ROUND($G28*Settings!$B$5,0) | K28: Health | L28: 0.08 | M28: =ROUND($L28*Settings!$B$3,0) | N28: =ROUND($L28*Settings!$B$4,0) | O28: =ROUND($L28*Settings!$B$5,0) | Q28: 0 | R28: =ROUND($Q28*Settings!$B$3,0) | S28: =ROUND($Q28*Settings!$B$4,0) | T28: =ROUND($Q28*Settings!$B$5,0) | V28: 0 | Z28: 0 | AA28: Adds premium food supply | AB28: v5: organic 1 week $70 | AC28: MVP | AD28: Food supply (not a meal)
A29: A028 | B29: Air One Supermarket | C29: Buy 4 Weeks of Groceries | D29: Food | E29: Fridge required | F29: 1 | G29: 1.3 | H29: =ROUND($G29*Settings!$B$3,0) | I29: =ROUND($G29*Settings!$B$4,0) | J29: =ROUND($G29*Settings!$B$5,0) | K29: Health | L29: 0.1 | M29: =ROUND($L29*Settings!$B$3,0) | N29: =ROUND($L29*Settings!$B$4,0) | O29: =ROUND($L29*Settings!$B$5,0) | Q29: 0 | R29: =ROUND($Q29*Settings!$B$3,0) | S29: =ROUND($Q29*Settings!$B$4,0) | T29: =ROUND($Q29*Settings!$B$5,0) | V29: 0 | Z29: 0 | AA29: Adds 4 weeks food supply | AB29: v5: 4 weeks $130; fridge required | AC29: MVP | AD29: Food supply (not a meal)
A30: A029 | B30: Air One Supermarket | C30: Buy $22 Smoothie | D30: Food | E30: None | F30: 1 | G30: 0.25 | H30: =ROUND($G30*Settings!$B$3,0) | I30: =ROUND($G30*Settings!$B$4,0) | J30: =ROUND($G30*Settings!$B$5,0) | K30: Health | L30: 0.05 | M30: =ROUND($L30*Settings!$B$3,0) | N30: =ROUND($L30*Settings!$B$4,0) | O30: =ROUND($L30*Settings!$B$5,0) | P30: Happiness | Q30: 0.02 | R30: =ROUND($Q30*Settings!$B$3,0) | S30: =ROUND($Q30*Settings!$B$4,0) | T30: =ROUND($Q30*Settings!$B$5,0) | V30: 0 | Z30: 0 | AA30: Fills hunger lightly | AB30: Expensive joke item | AC30: MVP | AD30: Eat
A31: A030 | B31: Air One Supermarket | C31: Judge Window Shoppers | D31: Personality | E31: None | F31: 1 | G31: 0 | H31: =ROUND($G31*Settings!$B$3,0) | I31: =ROUND($G31*Settings!$B$4,0) | J31: =ROUND($G31*Settings!$B$5,0) | K31: Enlightenment | L31: 0.03 | M31: =ROUND($L31*Settings!$B$3,0) | N31: =ROUND($L31*Settings!$B$4,0) | O31: =ROUND($L31*Settings!$B$5,0) | P31: Coolness Factor | Q31: 0.02 | R31: =ROUND($Q31*Settings!$B$3,0) | S31: =ROUND($Q31*Settings!$B$4,0) | T31: =ROUND($Q31*Settings!$B$5,0) | V31: 0 | Z31: 0 | AB31: Small hybrid | AC31: MVP
A32: A031 | B32: Air One Supermarket | C32: Buy Meal Prep Ingredients | D32: Food | E32: Fridge + stove | F32: 1 | G32: 0.6 | H32: =ROUND($G32*Settings!$B$3,0) | I32: =ROUND($G32*Settings!$B$4,0) | J32: =ROUND($G32*Settings!$B$5,0) | K32: Health | L32: 0.1 | M32: =ROUND($L32*Settings!$B$3,0) | N32: =ROUND($L32*Settings!$B$4,0) | O32: =ROUND($L32*Settings!$B$5,0) | Q32: 0 | R32: =ROUND($Q32*Settings!$B$3,0) | S32: =ROUND($Q32*Settings!$B$4,0) | T32: =ROUND($Q32*Settings!$B$5,0) | V32: 0 | Z32: 0 | AA32: Better food efficiency at home | AB32: Mid/late food route | AC32: MVP | AD32: Food supply (not a meal)
A33: A032 | B33: Air One Supermarket | C33: Extreme Clean Eating | D33: Food | E33: None | F33: 1 | G33: 0.8 | H33: =ROUND($G33*Settings!$B$3,0) | I33: =ROUND($G33*Settings!$B$4,0) | J33: =ROUND($G33*Settings!$B$5,0) | K33: Health | L33: 0.12 | M33: =ROUND($L33*Settings!$B$3,0) | N33: =ROUND($L33*Settings!$B$4,0) | O33: =ROUND($L33*Settings!$B$5,0) | Q33: 0 | R33: =ROUND($Q33*Settings!$B$3,0) | S33: =ROUND($Q33*Settings!$B$4,0) | T33: =ROUND($Q33*Settings!$B$5,0) | V33: 0 | W33: Happiness | X33: 0.025 | Z33: 0 | AB33: High health, slight fun loss | AC33: MVP | AD33: Eat
A34: A033 | B34: Air One Supermarket | C34: Work | D34: Work | E34: Job assigned at Corporate Soul Exchange | F34: 2 | G34: 0 | H34: =ROUND($G34*Settings!$B$3,0) | I34: =ROUND($G34*Settings!$B$4,0) | J34: =ROUND($G34*Settings!$B$5,0) | K34: From job tier | L34: 0 | M34: =ROUND($L34*Settings!$B$3,0) | N34: =ROUND($L34*Settings!$B$4,0) | O34: =ROUND($L34*Settings!$B$5,0) | P34: From job tier | Q34: 0 | R34: =ROUND($Q34*Settings!$B$3,0) | S34: =ROUND($Q34*Settings!$B$4,0) | T34: =ROUND($Q34*Settings!$B$5,0) | V34: 0 | W34: Health | X34: 0.02 | Y34: Happiness | Z34: 0.02 | AA34: One work click (2 Time Units). Money and Career come from the current job tier in Jobs_Named / Job_Progression, NOT from this row. Money is then multiplied by this building's Money Multiplier. Career is subject to the per-turn diminishing-returns rule in Settings. | AB34: v6 BUG FIX: this row used to grant Money 6%B ($6) and Career 4-6%B on top of the job tier's own pay and Career, which double-counted Career and contradicted the v5 wage table ($40-$400 per click). Both are now zero here. | AC34: MVP | AD34: Work | AH34: 1.1 | AI34: Money/Career now sourced from job tier; building Money Multiplier added
A35: A034 | B35: Regret Burger | C35: Regret Burger Classic | D35: Food | E35: None | F35: 1 | G35: 0.15 | H35: =ROUND($G35*Settings!$B$3,0) | I35: =ROUND($G35*Settings!$B$4,0) | J35: =ROUND($G35*Settings!$B$5,0) | K35: Happiness | L35: 0.04 | M35: =ROUND($L35*Settings!$B$3,0) | N35: =ROUND($L35*Settings!$B$4,0) | O35: =ROUND($L35*Settings!$B$5,0) | Q35: 0 | R35: =ROUND($Q35*Settings!$B$3,0) | S35: =ROUND($Q35*Settings!$B$4,0) | T35: =ROUND($Q35*Settings!$B$5,0) | V35: 0 | W35: Health | X35: 0.025 | Z35: 0 | AA35: Fills hunger | AB35: v5: repriced to the rebuilt money economy | AC35: MVP | AD35: Eat
A36: A035 | B36: Regret Burger | C36: Double Regret Deluxe | D36: Food | E36: None | F36: 1 | G36: 0.22 | H36: =ROUND($G36*Settings!$B$3,0) | I36: =ROUND($G36*Settings!$B$4,0) | J36: =ROUND($G36*Settings!$B$5,0) | K36: Happiness | L36: 0.07 | M36: =ROUND($L36*Settings!$B$3,0) | N36: =ROUND($L36*Settings!$B$4,0) | O36: =ROUND($L36*Settings!$B$5,0) | Q36: 0 | R36: =ROUND($Q36*Settings!$B$3,0) | S36: =ROUND($Q36*Settings!$B$4,0) | T36: =ROUND($Q36*Settings!$B$5,0) | V36: 0 | W36: Health | X36: 0.05 | Z36: 0 | AA36: Fills hunger | AB36: v5: repriced to the rebuilt money economy | AC36: MVP | AD36: Eat
A37: A036 | B37: Regret Burger | C37: Shame Shake | D37: Food | E37: None | F37: 1 | G37: 0.18 | H37: =ROUND($G37*Settings!$B$3,0) | I37: =ROUND($G37*Settings!$B$4,0) | J37: =ROUND($G37*Settings!$B$5,0) | K37: Happiness | L37: 0.05 | M37: =ROUND($L37*Settings!$B$3,0) | N37: =ROUND($L37*Settings!$B$4,0) | O37: =ROUND($L37*Settings!$B$5,0) | Q37: 0 | R37: =ROUND($Q37*Settings!$B$3,0) | S37: =ROUND($Q37*Settings!$B$4,0) | T37: =ROUND($Q37*Settings!$B$5,0) | V37: 0 | W37: Health | X37: 0.04 | Y37: Money | Z37: 0.02 | AA37: Fills hunger | AB37: v5: repriced to the rebuilt money economy | AC37: MVP | AD37: Eat
A38: A037 | B38: Regret Burger | C38: Doomscroll Fries | D38: Food | E38: None | F38: 1 | G38: 0.15 | H38: =ROUND($G38*Settings!$B$3,0) | I38: =ROUND($G38*Settings!$B$4,0) | J38: =ROUND($G38*Settings!$B$5,0) | K38: Happiness | L38: 0.04 | M38: =ROUND($L38*Settings!$B$3,0) | N38: =ROUND($L38*Settings!$B$4,0) | O38: =ROUND($L38*Settings!$B$5,0) | Q38: 0 | R38: =ROUND($Q38*Settings!$B$3,0) | S38: =ROUND($Q38*Settings!$B$4,0) | T38: =ROUND($Q38*Settings!$B$5,0) | V38: 0 | W38: Health | X38: 0.03 | Y38: Critical Thinking | Z38: 0.025 | AA38: Fills hunger | AB38: v5: repriced to the rebuilt money economy | AC38: MVP | AD38: Eat
A39: A038 | B39: Regret Burger | C39: Emotional Support Nuggets | D39: Food | E39: None | F39: 1 | G39: 0.2 | H39: =ROUND($G39*Settings!$B$3,0) | I39: =ROUND($G39*Settings!$B$4,0) | J39: =ROUND($G39*Settings!$B$5,0) | K39: Happiness | L39: 0.06 | M39: =ROUND($L39*Settings!$B$3,0) | N39: =ROUND($L39*Settings!$B$4,0) | O39: =ROUND($L39*Settings!$B$5,0) | Q39: 0 | R39: =ROUND($Q39*Settings!$B$3,0) | S39: =ROUND($Q39*Settings!$B$4,0) | T39: =ROUND($Q39*Settings!$B$5,0) | V39: 0 | W39: Health | X39: 0.04 | Z39: 0 | AA39: Fills hunger | AB39: v5: repriced to the rebuilt money economy | AC39: MVP | AD39: Eat
A40: A039 | B40: Regret Burger | C40: Coupon Meal | D40: Food | E40: None | F40: 1 | G40: 0.08 | H40: =ROUND($G40*Settings!$B$3,0) | I40: =ROUND($G40*Settings!$B$4,0) | J40: =ROUND($G40*Settings!$B$5,0) | K40: Happiness | L40: 0.025 | M40: =ROUND($L40*Settings!$B$3,0) | N40: =ROUND($L40*Settings!$B$4,0) | O40: =ROUND($L40*Settings!$B$5,0) | Q40: 0 | R40: =ROUND($Q40*Settings!$B$3,0) | S40: =ROUND($Q40*Settings!$B$4,0) | T40: =ROUND($Q40*Settings!$B$5,0) | V40: 0 | W40: Health | X40: 0.035 | Z40: 0 | AA40: Fills hunger | AB40: v5: repriced to the rebuilt money economy | AC40: MVP | AD40: Eat
A41: A040 | B41: Regret Burger | C41: Late Night Drive Thru | D41: Food | E41: None | F41: 1 | G41: 0.25 | H41: =ROUND($G41*Settings!$B$3,0) | I41: =ROUND($G41*Settings!$B$4,0) | J41: =ROUND($G41*Settings!$B$5,0) | K41: Happiness | L41: 0.08 | M41: =ROUND($L41*Settings!$B$3,0) | N41: =ROUND($L41*Settings!$B$4,0) | O41: =ROUND($L41*Settings!$B$5,0) | Q41: 0 | R41: =ROUND($Q41*Settings!$B$3,0) | S41: =ROUND($Q41*Settings!$B$4,0) | T41: =ROUND($Q41*Settings!$B$5,0) | V41: 0 | W41: Health | X41: 0.06 | Z41: 0 | AA41: Fills hunger | AB41: v5: repriced to the rebuilt money economy | AC41: MVP | AD41: Eat
A42: A041 | B42: Regret Burger | C42: Work | D42: Work | E42: Job assigned at Corporate Soul Exchange | F42: 2 | G42: 0 | H42: =ROUND($G42*Settings!$B$3,0) | I42: =ROUND($G42*Settings!$B$4,0) | J42: =ROUND($G42*Settings!$B$5,0) | K42: From job tier | L42: 0 | M42: =ROUND($L42*Settings!$B$3,0) | N42: =ROUND($L42*Settings!$B$4,0) | O42: =ROUND($L42*Settings!$B$5,0) | P42: From job tier | Q42: 0 | R42: =ROUND($Q42*Settings!$B$3,0) | S42: =ROUND($Q42*Settings!$B$4,0) | T42: =ROUND($Q42*Settings!$B$5,0) | V42: 0 | W42: Health | X42: 0.025 | Y42: Happiness | Z42: 0.025 | AA42: One work click (2 Time Units). Money and Career come from the current job tier in Jobs_Named / Job_Progression, NOT from this row. Money is then multiplied by this building's Money Multiplier. Career is subject to the per-turn diminishing-returns rule in Settings. | AB42: v6 BUG FIX: this row used to grant Money 6%B ($6) and Career 4-6%B on top of the job tier's own pay and Career, which double-counted Career and contradicted the v5 wage table ($40-$400 per click). Both are now zero here. | AC42: MVP | AD42: Work | AH42: 1.1 | AI42: Money/Career now sourced from job tier; building Money Multiplier added
A43: A042 | B43: Bro Science Gym | C43: Cardio Session | D43: Health | E43: None | F43: 1 | G43: 0.05 | H43: =ROUND($G43*Settings!$B$3,0) | I43: =ROUND($G43*Settings!$B$4,0) | J43: =ROUND($G43*Settings!$B$5,0) | K43: Health | L43: 0.06 | M43: =ROUND($L43*Settings!$B$3,0) | N43: =ROUND($L43*Settings!$B$4,0) | O43: =ROUND($L43*Settings!$B$5,0) | P43: Connection | Q43: 0.02 | R43: =ROUND($Q43*Settings!$B$3,0) | S43: =ROUND($Q43*Settings!$B$4,0) | T43: =ROUND($Q43*Settings!$B$5,0) | V43: 0 | Z43: 0 | AB43: Standard health action | v6.1: restored the v5.1 price that matches the painted menu ($5). | AC43: MVP | AI43: Health 0.05 -> 0.06; +Connection 2%B (you talk to people at the gym)
A44: A043 | B44: Bro Science Gym | C44: Chest Day | D44: Health | E44: None | F44: 1 | G44: 0.1 | H44: =ROUND($G44*Settings!$B$3,0) | I44: =ROUND($G44*Settings!$B$4,0) | J44: =ROUND($G44*Settings!$B$5,0) | K44: Health | L44: 0.05 | M44: =ROUND($L44*Settings!$B$3,0) | N44: =ROUND($L44*Settings!$B$4,0) | O44: =ROUND($L44*Settings!$B$5,0) | P44: Coolness Factor | Q44: 0.03 | R44: =ROUND($Q44*Settings!$B$3,0) | S44: =ROUND($Q44*Settings!$B$4,0) | T44: =ROUND($Q44*Settings!$B$5,0) | V44: 0 | W44: None | X44: 0 | Z44: 0 | AB44: v6: the old -2%B Happiness penalty is replaced by a flat Happiness +1 and Enlightenment -1. Flat points, applied after the percentage gains, not scaled by B and not modified by personality. | v6.1: restored the v5.1 price that matches the painted menu ($10). | AC44: MVP | AG44: Happiness +1, Enlightenment -1 | AI44: Happiness penalty replaced by flat Happiness +1 / Enlightenment -1
A45: A044 | B45: Bro Science Gym | C45: Treninator Bootcamp | D45: Health | E45: None | F45: 2 | G45: 0.25 | H45: =ROUND($G45*Settings!$B$3,0) | I45: =ROUND($G45*Settings!$B$4,0) | J45: =ROUND($G45*Settings!$B$5,0) | K45: Health | L45: 0.12 | M45: =ROUND($L45*Settings!$B$3,0) | N45: =ROUND($L45*Settings!$B$4,0) | O45: =ROUND($L45*Settings!$B$5,0) | P45: Connection | Q45: 0.03 | R45: =ROUND($Q45*Settings!$B$3,0) | S45: =ROUND($Q45*Settings!$B$4,0) | T45: =ROUND($Q45*Settings!$B$5,0) | V45: 0 | W45: Happiness | X45: 0.025 | Z45: 0 | AB45: Strong health route | v6.1: restored the v5.1 price that matches the painted menu ($25). | AC45: MVP | AI45: Health 0.10 -> 0.12; +Connection 3%B
A46: A045 | B46: Bro Science Gym | C46: Buy Suspicious Test Booster | D46: Shopping | E46: None | F46: 1 | G46: 0.4 | H46: =ROUND($G46*Settings!$B$3,0) | I46: =ROUND($G46*Settings!$B$4,0) | J46: =ROUND($G46*Settings!$B$5,0) | K46: Health | L46: 0.08 | M46: =ROUND($L46*Settings!$B$3,0) | N46: =ROUND($L46*Settings!$B$4,0) | O46: =ROUND($L46*Settings!$B$5,0) | P46: Coolness Factor | Q46: 0.05 | R46: =ROUND($Q46*Settings!$B$3,0) | S46: =ROUND($Q46*Settings!$B$4,0) | T46: =ROUND($Q46*Settings!$B$5,0) | V46: 0 | W46: Happiness | X46: 0.04 | Z46: 0 | AB46: Powerful, dumb | v6.1: restored the v5.1 price that matches the painted menu ($40). | AC46: MVP
A47: A046 | B47: Bro Science Gym | C47: Flex in Mirror | D47: Coolness | E47: None | F47: 1 | G47: 0 | H47: =ROUND($G47*Settings!$B$3,0) | I47: =ROUND($G47*Settings!$B$4,0) | J47: =ROUND($G47*Settings!$B$5,0) | K47: Coolness Factor | L47: 0.05 | M47: =ROUND($L47*Settings!$B$3,0) | N47: =ROUND($L47*Settings!$B$4,0) | O47: =ROUND($L47*Settings!$B$5,0) | P47: Happiness | Q47: 0.025 | R47: =ROUND($Q47*Settings!$B$3,0) | S47: =ROUND($Q47*Settings!$B$4,0) | T47: =ROUND($Q47*Settings!$B$5,0) | V47: 0 | Z47: 0 | AB47: Free coolness | AC47: MVP
A48: A047 | B48: Bro Science Gym | C48: Skip Leg Day | D48: Coolness | E48: None | F48: 1 | G48: 0 | H48: =ROUND($G48*Settings!$B$3,0) | I48: =ROUND($G48*Settings!$B$4,0) | J48: =ROUND($G48*Settings!$B$5,0) | K48: Coolness Factor | L48: 0.04 | M48: =ROUND($L48*Settings!$B$3,0) | N48: =ROUND($L48*Settings!$B$4,0) | O48: =ROUND($L48*Settings!$B$5,0) | Q48: 0 | R48: =ROUND($Q48*Settings!$B$3,0) | S48: =ROUND($Q48*Settings!$B$4,0) | T48: =ROUND($Q48*Settings!$B$5,0) | V48: 0 | W48: Health | X48: 0.025 | Z48: 0 | AB48: Joke tradeoff | AC48: MVP
A49: A048 | B49: Bro Science Gym | C49: Personal Best Challenge | D49: Health | E49: None | F49: 2 | G49: 0.15 | H49: =ROUND($G49*Settings!$B$3,0) | I49: =ROUND($G49*Settings!$B$4,0) | J49: =ROUND($G49*Settings!$B$5,0) | K49: Health | L49: 0.1 | M49: =ROUND($L49*Settings!$B$3,0) | N49: =ROUND($L49*Settings!$B$4,0) | O49: =ROUND($L49*Settings!$B$5,0) | P49: Coolness Factor | Q49: 0.04 | R49: =ROUND($Q49*Settings!$B$3,0) | S49: =ROUND($Q49*Settings!$B$4,0) | T49: =ROUND($Q49*Settings!$B$5,0) | V49: 0 | W49: Happiness | X49: 0.03 | Z49: 0 | AB49: Strong but tiring | v6.1: restored the v5.1 price that matches the painted menu ($15). | AC49: MVP | AG49: Connection +1 | AI49: Health 0.08 -> 0.10; flat Connection +1 (someone spots you)
A50: A049 | B50: Bro Science Gym | C50: Work | D50: Work | E50: Job assigned at Corporate Soul Exchange | F50: 2 | G50: 0 | H50: =ROUND($G50*Settings!$B$3,0) | I50: =ROUND($G50*Settings!$B$4,0) | J50: =ROUND($G50*Settings!$B$5,0) | K50: From job tier | L50: 0 | M50: =ROUND($L50*Settings!$B$3,0) | N50: =ROUND($L50*Settings!$B$4,0) | O50: =ROUND($L50*Settings!$B$5,0) | P50: From job tier | Q50: 0 | R50: =ROUND($Q50*Settings!$B$3,0) | S50: =ROUND($Q50*Settings!$B$4,0) | T50: =ROUND($Q50*Settings!$B$5,0) | V50: 0 | W50: Health | X50: 0.015 | Y50: Happiness | Z50: 0.02 | AA50: One work click (2 Time Units). Money and Career come from the current job tier in Jobs_Named / Job_Progression, NOT from this row. Money is then multiplied by this building's Money Multiplier. Career is subject to the per-turn diminishing-returns rule in Settings. | AB50: v6 BUG FIX: this row used to grant Money 6%B ($6) and Career 4-6%B on top of the job tier's own pay and Career, which double-counted Career and contradicted the v5 wage table ($40-$400 per click). Both are now zero here. | AC50: MVP | AD50: Work | AH50: 1.2 | AI50: Money/Career now sourced from job tier; building Money Multiplier added
A51: A050 | B51: Bad Decisions Club | C51: Dance | D51: Social | E51: Dressy clothes | F51: 1 | G51: 0.05 | H51: =ROUND($G51*Settings!$B$3,0) | I51: =ROUND($G51*Settings!$B$4,0) | J51: =ROUND($G51*Settings!$B$5,0) | K51: Connection | L51: 0.05 | M51: =ROUND($L51*Settings!$B$3,0) | N51: =ROUND($L51*Settings!$B$4,0) | O51: =ROUND($L51*Settings!$B$5,0) | P51: Coolness Factor | Q51: 0.04 | R51: =ROUND($Q51*Settings!$B$3,0) | S51: =ROUND($Q51*Settings!$B$4,0) | T51: =ROUND($Q51*Settings!$B$5,0) | V51: 0 | Z51: 0 | AB51: Core club action | AC51: MVP
A52: A051 | B52: Bad Decisions Club | C52: Flirt Recklessly | D52: Social | E52: Dressy clothes | F52: 1 | G52: 0.03 | H52: =ROUND($G52*Settings!$B$3,0) | I52: =ROUND($G52*Settings!$B$4,0) | J52: =ROUND($G52*Settings!$B$5,0) | K52: Connection | L52: 0.08 | M52: =ROUND($L52*Settings!$B$3,0) | N52: =ROUND($L52*Settings!$B$4,0) | O52: =ROUND($L52*Settings!$B$5,0) | P52: Coolness Factor | Q52: 0.04 | R52: =ROUND($Q52*Settings!$B$3,0) | S52: =ROUND($Q52*Settings!$B$4,0) | T52: =ROUND($Q52*Settings!$B$5,0) | V52: 0 | W52: Critical Thinking | X52: 0.04 | Z52: 0 | AB52: Fast social gain | AC52: MVP
A53: A052 | B53: Bad Decisions Club | C53: Get Digits | D53: Social | E53: Dressy clothes | F53: 1 | G53: 0.02 | H53: =ROUND($G53*Settings!$B$3,0) | I53: =ROUND($G53*Settings!$B$4,0) | J53: =ROUND($G53*Settings!$B$5,0) | K53: Connection | L53: 0.06 | M53: =ROUND($L53*Settings!$B$3,0) | N53: =ROUND($L53*Settings!$B$4,0) | O53: =ROUND($L53*Settings!$B$5,0) | Q53: 0 | R53: =ROUND($Q53*Settings!$B$3,0) | S53: =ROUND($Q53*Settings!$B$4,0) | T53: =ROUND($Q53*Settings!$B$5,0) | V53: 0 | W53: Critical Thinking | X53: 0.025 | Z53: 0 | AB53: Simple connection action | AC53: MVP
A54: A053 | B54: Bad Decisions Club | C54: Order Shots | D54: Food/Drink | E54: Dressy clothes | F54: 1 | G54: 0.08 | H54: =ROUND($G54*Settings!$B$3,0) | I54: =ROUND($G54*Settings!$B$4,0) | J54: =ROUND($G54*Settings!$B$5,0) | K54: Happiness | L54: 0.06 | M54: =ROUND($L54*Settings!$B$3,0) | N54: =ROUND($L54*Settings!$B$4,0) | O54: =ROUND($L54*Settings!$B$5,0) | P54: Connection | Q54: 0.03 | R54: =ROUND($Q54*Settings!$B$3,0) | S54: =ROUND($Q54*Settings!$B$4,0) | T54: =ROUND($Q54*Settings!$B$5,0) | V54: 0 | W54: Health | X54: 0.05 | Y54: Money | Z54: 0.02 | AB54: Club should drain health/money | AC54: MVP | AD54: Eat
A55: A054 | B55: Bad Decisions Club | C55: VIP Lounge | D55: Social | E55: Dressy clothes + Coolness threshold | F55: 2 | G55: 0.16 | H55: =ROUND($G55*Settings!$B$3,0) | I55: =ROUND($G55*Settings!$B$4,0) | J55: =ROUND($G55*Settings!$B$5,0) | K55: Coolness Factor | L55: 0.1 | M55: =ROUND($L55*Settings!$B$3,0) | N55: =ROUND($L55*Settings!$B$4,0) | O55: =ROUND($L55*Settings!$B$5,0) | P55: Connection | Q55: 0.08 | R55: =ROUND($Q55*Settings!$B$3,0) | S55: =ROUND($Q55*Settings!$B$4,0) | T55: =ROUND($Q55*Settings!$B$5,0) | V55: 0 | Z55: 0 | AB55: Premium social route | AC55: MVP
A56: A055 | B56: Bad Decisions Club | C56: Go Home With Stranger | D56: Social | E56: Dressy clothes | F56: 2 | G56: 0 | H56: =ROUND($G56*Settings!$B$3,0) | I56: =ROUND($G56*Settings!$B$4,0) | J56: =ROUND($G56*Settings!$B$5,0) | K56: Connection | L56: 0.1 | M56: =ROUND($L56*Settings!$B$3,0) | N56: =ROUND($L56*Settings!$B$4,0) | O56: =ROUND($L56*Settings!$B$5,0) | Q56: 0 | R56: =ROUND($Q56*Settings!$B$3,0) | S56: =ROUND($Q56*Settings!$B$4,0) | T56: =ROUND($Q56*Settings!$B$5,0) | V56: 0 | W56: Critical Thinking | X56: 0.06 | Z56: 0 | AB56: Big connection, bad judgment | AC56: MVP
A57: A056 | B57: Bad Decisions Club | C57: Brag About Side Hustle | D57: Coolness | E57: Dressy clothes | F57: 1 | G57: 0 | H57: =ROUND($G57*Settings!$B$3,0) | I57: =ROUND($G57*Settings!$B$4,0) | J57: =ROUND($G57*Settings!$B$5,0) | K57: Coolness Factor | L57: 0.04 | M57: =ROUND($L57*Settings!$B$3,0) | N57: =ROUND($L57*Settings!$B$4,0) | O57: =ROUND($L57*Settings!$B$5,0) | Q57: 0 | R57: =ROUND($Q57*Settings!$B$3,0) | S57: =ROUND($Q57*Settings!$B$4,0) | T57: =ROUND($Q57*Settings!$B$5,0) | V57: 0 | W57: Connection | X57: 0.025 | Z57: 0 | AB57: Minor comedy tradeoff | AC57: MVP
A58: A057 | B58: Bad Decisions Club | C58: Work | D58: Work | E58: Job assigned at Corporate Soul Exchange | F58: 2 | G58: 0 | H58: =ROUND($G58*Settings!$B$3,0) | I58: =ROUND($G58*Settings!$B$4,0) | J58: =ROUND($G58*Settings!$B$5,0) | K58: From job tier | L58: 0 | M58: =ROUND($L58*Settings!$B$3,0) | N58: =ROUND($L58*Settings!$B$4,0) | O58: =ROUND($L58*Settings!$B$5,0) | P58: From job tier | Q58: 0 | R58: =ROUND($Q58*Settings!$B$3,0) | S58: =ROUND($Q58*Settings!$B$4,0) | T58: =ROUND($Q58*Settings!$B$5,0) | V58: 0 | W58: Health | X58: 0.03 | Y58: Happiness | Z58: 0.02 | AA58: One work click (2 Time Units). Money and Career come from the current job tier in Jobs_Named / Job_Progression, NOT from this row. Money is then multiplied by this building's Money Multiplier. Career is subject to the per-turn diminishing-returns rule in Settings. | AB58: v6 BUG FIX: this row used to grant Money 6%B ($6) and Career 4-6%B on top of the job tier's own pay and Career, which double-counted Career and contradicted the v5 wage table ($40-$400 per click). Both are now zero here. | AC58: MVP | AD58: Work | AH58: 1.2 | AI58: Money/Career now sourced from job tier; building Money Multiplier added
A59: A058 | B59: Re-Education Temple | C59: Buy My Camp | D59: Unlock | E59: Money threshold | F59: 1 | G59: 0.2 | H59: =ROUND($G59*Settings!$B$3,0) | I59: =ROUND($G59*Settings!$B$4,0) | J59: =ROUND($G59*Settings!$B$5,0) | K59: Enlightenment | L59: 0.05 | M59: =ROUND($L59*Settings!$B$3,0) | N59: =ROUND($L59*Settings!$B$4,0) | O59: =ROUND($L59*Settings!$B$5,0) | Q59: 0 | R59: =ROUND($Q59*Settings!$B$3,0) | S59: =ROUND($Q59*Settings!$B$4,0) | T59: =ROUND($Q59*Settings!$B$5,0) | V59: 0 | Z59: 0 | AA59: Unlocks advanced temple actions; boosts enlightenment when relaxing at home | AB59: Key temple purchase | AC59: MVP
A60: A059 | B60: Re-Education Temple | C60: Surrender Thought | D60: Enlightenment | E60: None | F60: 1 | G60: 0 | H60: =ROUND($G60*Settings!$B$3,0) | I60: =ROUND($G60*Settings!$B$4,0) | J60: =ROUND($G60*Settings!$B$5,0) | K60: Enlightenment | L60: 0.08 | M60: =ROUND($L60*Settings!$B$3,0) | N60: =ROUND($L60*Settings!$B$4,0) | O60: =ROUND($L60*Settings!$B$5,0) | Q60: 0 | R60: =ROUND($Q60*Settings!$B$3,0) | S60: =ROUND($Q60*Settings!$B$4,0) | T60: =ROUND($Q60*Settings!$B$5,0) | V60: 0 | W60: Critical Thinking | X60: 0.04 | Z60: 0 | AB60: Strong but suspicious | AC60: MVP
A61: A060 | B61: Re-Education Temple | C61: Join Group Chant | D61: Social | E61: None | F61: 1 | G61: 0.02 | H61: =ROUND($G61*Settings!$B$3,0) | I61: =ROUND($G61*Settings!$B$4,0) | J61: =ROUND($G61*Settings!$B$5,0) | K61: Enlightenment | L61: 0.06 | M61: =ROUND($L61*Settings!$B$3,0) | N61: =ROUND($L61*Settings!$B$4,0) | O61: =ROUND($L61*Settings!$B$5,0) | P61: Connection | Q61: 0.04 | R61: =ROUND($Q61*Settings!$B$3,0) | S61: =ROUND($Q61*Settings!$B$4,0) | T61: =ROUND($Q61*Settings!$B$5,0) | V61: 0 | Z61: 0 | AB61: Temple social route | AC61: MVP
A62: A061 | B62: Re-Education Temple | C62: Report Doubt | D62: Enlightenment | E62: None | F62: 1 | G62: 0 | H62: =ROUND($G62*Settings!$B$3,0) | I62: =ROUND($G62*Settings!$B$4,0) | J62: =ROUND($G62*Settings!$B$5,0) | K62: Enlightenment | L62: 0.05 | M62: =ROUND($L62*Settings!$B$3,0) | N62: =ROUND($L62*Settings!$B$4,0) | O62: =ROUND($L62*Settings!$B$5,0) | Q62: 0 | R62: =ROUND($Q62*Settings!$B$3,0) | S62: =ROUND($Q62*Settings!$B$4,0) | T62: =ROUND($Q62*Settings!$B$5,0) | V62: 0 | W62: Critical Thinking | X62: 0.03 | Z62: 0 | AB62: Cult satire | AC62: MVP
A63: A062 | B63: Re-Education Temple | C63: Achieve Inner Peace | D63: Enlightenment | E63: Enlightenment threshold | F63: 2 | G63: 0.04 | H63: =ROUND($G63*Settings!$B$3,0) | I63: =ROUND($G63*Settings!$B$4,0) | J63: =ROUND($G63*Settings!$B$5,0) | K63: Enlightenment | L63: 0.12 | M63: =ROUND($L63*Settings!$B$3,0) | N63: =ROUND($L63*Settings!$B$4,0) | O63: =ROUND($L63*Settings!$B$5,0) | P63: Happiness | Q63: 0.04 | R63: =ROUND($Q63*Settings!$B$3,0) | S63: =ROUND($Q63*Settings!$B$4,0) | T63: =ROUND($Q63*Settings!$B$5,0) | V63: 0 | Z63: 0 | AB63: Premium enlightenment route | AC63: MVP | AD63: Relax
A64: A063 | B64: Re-Education Temple | C64: Guided Surrender Package | D64: Enlightenment | E64: None | F64: 1 | G64: 0.12 | H64: =ROUND($G64*Settings!$B$3,0) | I64: =ROUND($G64*Settings!$B$4,0) | J64: =ROUND($G64*Settings!$B$5,0) | K64: Enlightenment | L64: 0.1 | M64: =ROUND($L64*Settings!$B$3,0) | N64: =ROUND($L64*Settings!$B$4,0) | O64: =ROUND($L64*Settings!$B$5,0) | Q64: 0 | R64: =ROUND($Q64*Settings!$B$3,0) | S64: =ROUND($Q64*Settings!$B$4,0) | T64: =ROUND($Q64*Settings!$B$5,0) | V64: 0 | Z64: 0 | AB64: Paid enlightenment | AC64: MVP
A65: A064 | B65: Re-Education Temple | C65: Volunteer Service | D65: Social | E65: None | F65: 1 | G65: 0 | H65: =ROUND($G65*Settings!$B$3,0) | I65: =ROUND($G65*Settings!$B$4,0) | J65: =ROUND($G65*Settings!$B$5,0) | K65: Connection | L65: 0.05 | M65: =ROUND($L65*Settings!$B$3,0) | N65: =ROUND($L65*Settings!$B$4,0) | O65: =ROUND($L65*Settings!$B$5,0) | P65: Enlightenment | Q65: 0.05 | R65: =ROUND($Q65*Settings!$B$3,0) | S65: =ROUND($Q65*Settings!$B$4,0) | T65: =ROUND($Q65*Settings!$B$5,0) | V65: 0 | Z65: 0 | AB65: Good hybrid | AC65: MVP
A66: A065 | B66: Re-Education Temple | C66: Read Holy Fine Print | D66: Study | E66: None | F66: 1 | G66: 0 | H66: =ROUND($G66*Settings!$B$3,0) | I66: =ROUND($G66*Settings!$B$4,0) | J66: =ROUND($G66*Settings!$B$5,0) | K66: Critical Thinking | L66: 0.03 | M66: =ROUND($L66*Settings!$B$3,0) | N66: =ROUND($L66*Settings!$B$4,0) | O66: =ROUND($L66*Settings!$B$5,0) | P66: Enlightenment | Q66: 0.03 | R66: =ROUND($Q66*Settings!$B$3,0) | S66: =ROUND($Q66*Settings!$B$4,0) | T66: =ROUND($Q66*Settings!$B$5,0) | V66: 0 | Z66: 0 | AB66: Safer temple action | AC66: MVP
A67: A066 | B67: Re-Education Temple | C67: Work | D67: Work | E67: Job assigned at Corporate Soul Exchange | F67: 2 | G67: 0 | H67: =ROUND($G67*Settings!$B$3,0) | I67: =ROUND($G67*Settings!$B$4,0) | J67: =ROUND($G67*Settings!$B$5,0) | K67: From job tier | L67: 0 | M67: =ROUND($L67*Settings!$B$3,0) | N67: =ROUND($L67*Settings!$B$4,0) | O67: =ROUND($L67*Settings!$B$5,0) | P67: From job tier | Q67: 0 | R67: =ROUND($Q67*Settings!$B$3,0) | S67: =ROUND($Q67*Settings!$B$4,0) | T67: =ROUND($Q67*Settings!$B$5,0) | V67: 0 | W67: Happiness | X67: 0.02 | Y67: Critical Thinking | Z67: 0.02 | AA67: One work click (2 Time Units). Money and Career come from the current job tier in Jobs_Named / Job_Progression, NOT from this row. Money is then multiplied by this building's Money Multiplier. Career is subject to the per-turn diminishing-returns rule in Settings. | AB67: v6 BUG FIX: this row used to grant Money 6%B ($6) and Career 4-6%B on top of the job tier's own pay and Career, which double-counted Career and contradicted the v5 wage table ($40-$400 per click). Both are now zero here. | AC67: MVP | AD67: Work | AH67: 1.35 | AI67: Money/Career now sourced from job tier; building Money Multiplier added
A68: A067 | B68: High IQ University | C68: Take Class | D68: Study | E68: None | F68: 2 | G68: 0.08 | H68: =ROUND($G68*Settings!$B$3,0) | I68: =ROUND($G68*Settings!$B$4,0) | J68: =ROUND($G68*Settings!$B$5,0) | K68: Critical Thinking | L68: 0.08 | M68: =ROUND($L68*Settings!$B$3,0) | N68: =ROUND($L68*Settings!$B$4,0) | O68: =ROUND($L68*Settings!$B$5,0) | Q68: 0 | R68: =ROUND($Q68*Settings!$B$3,0) | S68: =ROUND($Q68*Settings!$B$4,0) | T68: =ROUND($Q68*Settings!$B$5,0) | V68: 0 | Z68: 0 | AA68: REMOVED — see Education_Paths and Job_Progression sheets | AB68: REMOVED IN v5. Replaced by the 30-course Education_Paths system (courses) / Job_Progression click gates (promotion). Do not implement. | AC68: REMOVED v5
A69: A068 | B69: High IQ University | C69: Study Group | D69: Study/Social | E69: None | F69: 2 | G69: 0.05 | H69: =ROUND($G69*Settings!$B$3,0) | I69: =ROUND($G69*Settings!$B$4,0) | J69: =ROUND($G69*Settings!$B$5,0) | K69: Critical Thinking | L69: 0.06 | M69: =ROUND($L69*Settings!$B$3,0) | N69: =ROUND($L69*Settings!$B$4,0) | O69: =ROUND($L69*Settings!$B$5,0) | P69: Connection | Q69: 0.04 | R69: =ROUND($Q69*Settings!$B$3,0) | S69: =ROUND($Q69*Settings!$B$4,0) | T69: =ROUND($Q69*Settings!$B$5,0) | V69: 0 | Z69: 0 | AA69: Degree progress | AB69: Good hybrid | AC69: MVP
A70: A069 | B70: High IQ University | C70: Flirt With Classmate | D70: Social | E70: None | F70: 1 | G70: 0.02 | H70: =ROUND($G70*Settings!$B$3,0) | I70: =ROUND($G70*Settings!$B$4,0) | J70: =ROUND($G70*Settings!$B$5,0) | K70: Connection | L70: 0.05 | M70: =ROUND($L70*Settings!$B$3,0) | N70: =ROUND($L70*Settings!$B$4,0) | O70: =ROUND($L70*Settings!$B$5,0) | Q70: 0 | R70: =ROUND($Q70*Settings!$B$3,0) | S70: =ROUND($Q70*Settings!$B$4,0) | T70: =ROUND($Q70*Settings!$B$5,0) | V70: 0 | Z70: 0 | AB70: No penalty, by request | AC70: MVP
A71: A070 | B71: High IQ University | C71: Finish Undergrad | D71: Milestone | E71: Degree progress + money | F71: 3 | G71: 0.25 | H71: =ROUND($G71*Settings!$B$3,0) | I71: =ROUND($G71*Settings!$B$4,0) | J71: =ROUND($G71*Settings!$B$5,0) | K71: Critical Thinking | L71: 0.15 | M71: =ROUND($L71*Settings!$B$3,0) | N71: =ROUND($L71*Settings!$B$4,0) | O71: =ROUND($L71*Settings!$B$5,0) | P71: Career | Q71: 0.1 | R71: =ROUND($Q71*Settings!$B$3,0) | S71: =ROUND($Q71*Settings!$B$4,0) | T71: =ROUND($Q71*Settings!$B$5,0) | V71: 0 | Z71: 0 | AA71: REMOVED — see Education_Paths and Job_Progression sheets | AB71: REMOVED IN v5. Replaced by the 30-course Education_Paths system (courses) / Job_Progression click gates (promotion). Do not implement. | AC71: REMOVED v5
A72: A071 | B72: High IQ University | C72: Finish Master's | D72: Milestone | E72: Undergrad + money | F72: 3 | G72: 0.45 | H72: =ROUND($G72*Settings!$B$3,0) | I72: =ROUND($G72*Settings!$B$4,0) | J72: =ROUND($G72*Settings!$B$5,0) | K72: Critical Thinking | L72: 0.2 | M72: =ROUND($L72*Settings!$B$3,0) | N72: =ROUND($L72*Settings!$B$4,0) | O72: =ROUND($L72*Settings!$B$5,0) | P72: Career | Q72: 0.15 | R72: =ROUND($Q72*Settings!$B$3,0) | S72: =ROUND($Q72*Settings!$B$4,0) | T72: =ROUND($Q72*Settings!$B$5,0) | V72: 0 | Z72: 0 | AA72: REMOVED — see Education_Paths and Job_Progression sheets | AB72: REMOVED IN v5. Replaced by the 30-course Education_Paths system (courses) / Job_Progression click gates (promotion). Do not implement. | AC72: REMOVED v5
A73: A072 | B73: High IQ University | C73: Finish PhD | D73: Milestone | E73: Master's + money | F73: 3 | G73: 0.8 | H73: =ROUND($G73*Settings!$B$3,0) | I73: =ROUND($G73*Settings!$B$4,0) | J73: =ROUND($G73*Settings!$B$5,0) | K73: Critical Thinking | L73: 0.25 | M73: =ROUND($L73*Settings!$B$3,0) | N73: =ROUND($L73*Settings!$B$4,0) | O73: =ROUND($L73*Settings!$B$5,0) | P73: Career | Q73: 0.2 | R73: =ROUND($Q73*Settings!$B$3,0) | S73: =ROUND($Q73*Settings!$B$4,0) | T73: =ROUND($Q73*Settings!$B$5,0) | V73: 0 | Z73: 0 | AA73: REMOVED — see Education_Paths and Job_Progression sheets | AB73: REMOVED IN v5. Replaced by the 30-course Education_Paths system (courses) / Job_Progression click gates (promotion). Do not implement. | AC73: REMOVED v5
A74: A073 | B74: High IQ University | C74: Cram All Night | D74: Study | E74: None | F74: 2 | G74: 0.04 | H74: =ROUND($G74*Settings!$B$3,0) | I74: =ROUND($G74*Settings!$B$4,0) | J74: =ROUND($G74*Settings!$B$5,0) | K74: Critical Thinking | L74: 0.1 | M74: =ROUND($L74*Settings!$B$3,0) | N74: =ROUND($L74*Settings!$B$4,0) | O74: =ROUND($L74*Settings!$B$5,0) | Q74: 0 | R74: =ROUND($Q74*Settings!$B$3,0) | S74: =ROUND($Q74*Settings!$B$4,0) | T74: =ROUND($Q74*Settings!$B$5,0) | V74: 0 | W74: Health | X74: 0.04 | Z74: 0 | AA74: Degree progress | AB74: Fast but unhealthy | AC74: MVP
A75: A074 | B75: High IQ University | C75: Debate Professor | D75: Study | E75: Critical Thinking threshold | F75: 1 | G75: 0 | H75: =ROUND($G75*Settings!$B$3,0) | I75: =ROUND($G75*Settings!$B$4,0) | J75: =ROUND($G75*Settings!$B$5,0) | K75: Critical Thinking | L75: 0.07 | M75: =ROUND($L75*Settings!$B$3,0) | N75: =ROUND($L75*Settings!$B$4,0) | O75: =ROUND($L75*Settings!$B$5,0) | P75: Coolness Factor | Q75: 0.02 | R75: =ROUND($Q75*Settings!$B$3,0) | S75: =ROUND($Q75*Settings!$B$4,0) | T75: =ROUND($Q75*Settings!$B$5,0) | V75: 0 | Z75: 0 | AB75: Nerd coolness | AC75: MVP
A76: A075 | B76: High IQ University | C76: Work | D76: Work | E76: Job assigned at Corporate Soul Exchange | F76: 2 | G76: 0 | H76: =ROUND($G76*Settings!$B$3,0) | I76: =ROUND($G76*Settings!$B$4,0) | J76: =ROUND($G76*Settings!$B$5,0) | K76: From job tier | L76: 0 | M76: =ROUND($L76*Settings!$B$3,0) | N76: =ROUND($L76*Settings!$B$4,0) | O76: =ROUND($L76*Settings!$B$5,0) | P76: From job tier | Q76: 0 | R76: =ROUND($Q76*Settings!$B$3,0) | S76: =ROUND($Q76*Settings!$B$4,0) | T76: =ROUND($Q76*Settings!$B$5,0) | V76: 0 | W76: Health | X76: 0.02 | Y76: Happiness | Z76: 0.02 | AA76: One work click (2 Time Units). Money and Career come from the current job tier in Jobs_Named / Job_Progression, NOT from this row. Money is then multiplied by this building's Money Multiplier. Career is subject to the per-turn diminishing-returns rule in Settings. | AB76: v6 BUG FIX: this row used to grant Money 6%B ($6) and Career 4-6%B on top of the job tier's own pay and Career, which double-counted Career and contradicted the v5 wage table ($40-$400 per click). Both are now zero here. | AC76: MVP | AD76: Work | AH76: 1.1 | AI76: Money/Career now sourced from job tier; building Money Multiplier added
A77: A076 | B77: Corporate Soul Exchange | C77: Get / Change Job | D77: Job | E77: Meet clothing/education requirements | F77: 1 | G77: 0 | H77: =ROUND($G77*Settings!$B$3,0) | I77: =ROUND($G77*Settings!$B$4,0) | J77: =ROUND($G77*Settings!$B$5,0) | K77: None | L77: 0 | M77: =ROUND($L77*Settings!$B$3,0) | N77: =ROUND($L77*Settings!$B$4,0) | O77: =ROUND($L77*Settings!$B$5,0) | Q77: 0 | R77: =ROUND($Q77*Settings!$B$3,0) | S77: =ROUND($Q77*Settings!$B$4,0) | T77: =ROUND($Q77*Settings!$B$5,0) | V77: 0 | Z77: 0 | AA77: Selects current job tier | AB77: v6: no longer grants Career. Changing job is a menu action, not an achievement. | AC77: MVP | AI77: Career 0.025 -> 0
A78: A077 | B78: Corporate Soul Exchange | C78: Work | D78: Work | E78: Current job assigned | F78: 2 | G78: 0 | H78: =ROUND($G78*Settings!$B$3,0) | I78: =ROUND($G78*Settings!$B$4,0) | J78: =ROUND($G78*Settings!$B$5,0) | K78: From job tier | L78: 0 | M78: =ROUND($L78*Settings!$B$3,0) | N78: =ROUND($L78*Settings!$B$4,0) | O78: =ROUND($L78*Settings!$B$5,0) | P78: From job tier | Q78: 0 | R78: =ROUND($Q78*Settings!$B$3,0) | S78: =ROUND($Q78*Settings!$B$4,0) | T78: =ROUND($Q78*Settings!$B$5,0) | V78: 0 | W78: Health | X78: 0.03 | Y78: Happiness | Z78: 0.03 | AA78: One work click (2 Time Units). Money and Career come from the current job tier in Jobs_Named / Job_Progression, NOT from this row. Money is then multiplied by this building's Money Multiplier. Career is subject to the per-turn diminishing-returns rule in Settings. | AB78: v6 BUG FIX: this row used to grant Money 6%B ($6) and Career 4-6%B on top of the job tier's own pay and Career, which double-counted Career and contradicted the v5 wage table ($40-$400 per click). Both are now zero here. | AC78: MVP | AD78: Work | AH78: 1 | AI78: Money/Career now sourced from job tier; building Money Multiplier added
A79: A078 | B79: Corporate Soul Exchange | C79: Update Resume Secretly | D79: Career | E79: Computer recommended | F79: 1 | G79: 0 | H79: =ROUND($G79*Settings!$B$3,0) | I79: =ROUND($G79*Settings!$B$4,0) | J79: =ROUND($G79*Settings!$B$5,0) | K79: Career | L79: 0.02 | M79: =ROUND($L79*Settings!$B$3,0) | N79: =ROUND($L79*Settings!$B$4,0) | O79: =ROUND($L79*Settings!$B$5,0) | P79: Critical Thinking | Q79: 0.03 | R79: =ROUND($Q79*Settings!$B$3,0) | S79: =ROUND($Q79*Settings!$B$4,0) | T79: =ROUND($Q79*Settings!$B$5,0) | V79: 0 | Z79: 0 | AB79: v6: Career cut from 5%B to 2%B and limited to once per turn. At 1 Time Unit and no money cost this was six uses a turn, +30 Career per turn at Short, and maxed Career in under four turns with no job, no education and no money. | AC79: MVP | AF79: 1 per turn | AI79: Career 0.05 -> 0.02; max 1 per turn
A80: A079 | B80: Corporate Soul Exchange | C80: Attend Team Building Event | D80: Work/Social | E80: Current job | F80: 2 | G80: 0 | H80: =ROUND($G80*Settings!$B$3,0) | I80: =ROUND($G80*Settings!$B$4,0) | J80: =ROUND($G80*Settings!$B$5,0) | K80: Career | L80: 0.03 | M80: =ROUND($L80*Settings!$B$3,0) | N80: =ROUND($L80*Settings!$B$4,0) | O80: =ROUND($L80*Settings!$B$5,0) | P80: Critical Thinking | Q80: 0.03 | R80: =ROUND($Q80*Settings!$B$3,0) | S80: =ROUND($Q80*Settings!$B$4,0) | T80: =ROUND($Q80*Settings!$B$5,0) | V80: 0 | W80: Happiness | X80: 0.04 | Y80: Connection | Z80: 0.03 | AB80: Fake socializing hurts real connection | AC80: MVP | AF80: 1 per turn | AI80: Career 0.05 -> 0.03; max 1 per turn
A81: A080 | B81: Corporate Soul Exchange | C81: Join Union Meeting to Fight Evil Corporation | D81: Social | E81: Current job | F81: 2 | G81: 0 | H81: =ROUND($G81*Settings!$B$3,0) | I81: =ROUND($G81*Settings!$B$4,0) | J81: =ROUND($G81*Settings!$B$5,0) | K81: Connection | L81: 0.06 | M81: =ROUND($L81*Settings!$B$3,0) | N81: =ROUND($L81*Settings!$B$4,0) | O81: =ROUND($L81*Settings!$B$5,0) | P81: Enlightenment | Q81: 0.04 | R81: =ROUND($Q81*Settings!$B$3,0) | S81: =ROUND($Q81*Settings!$B$4,0) | T81: =ROUND($Q81*Settings!$B$5,0) | V81: 0 | W81: Career | X81: 0.025 | Z81: 0 | AB81: Connection route added here | AC81: MVP
A82: A081 | B82: Corporate Soul Exchange | C82: Use Bathroom Timer | D82: Recovery | E82: Current job | F82: 1 | G82: 0 | H82: =ROUND($G82*Settings!$B$3,0) | I82: =ROUND($G82*Settings!$B$4,0) | J82: =ROUND($G82*Settings!$B$5,0) | K82: Health | L82: 0.025 | M82: =ROUND($L82*Settings!$B$3,0) | N82: =ROUND($L82*Settings!$B$4,0) | O82: =ROUND($L82*Settings!$B$5,0) | P82: Happiness | Q82: 0.02 | R82: =ROUND($Q82*Settings!$B$3,0) | S82: =ROUND($Q82*Settings!$B$4,0) | T82: =ROUND($Q82*Settings!$B$5,0) | V82: 0 | Z82: 0 | AA82: Counts as mini-relax | AB82: Tiny recovery | AC82: MVP | AD82: Relax
A83: A082 | B83: Corporate Soul Exchange | C83: Max Out Benefits | D83: Recovery | E83: Current job + benefits unlocked | F83: 1 | G83: 0 | H83: =ROUND($G83*Settings!$B$3,0) | I83: =ROUND($G83*Settings!$B$4,0) | J83: =ROUND($G83*Settings!$B$5,0) | K83: Happiness | L83: 0.06 | M83: =ROUND($L83*Settings!$B$3,0) | N83: =ROUND($L83*Settings!$B$4,0) | O83: =ROUND($L83*Settings!$B$5,0) | P83: Health | Q83: 0.06 | R83: =ROUND($Q83*Settings!$B$3,0) | S83: =ROUND($Q83*Settings!$B$4,0) | T83: =ROUND($Q83*Settings!$B$5,0) | V83: 0 | Z83: 0 | AB83: Good anti-burnout | AC83: MVP
A84: A083 | B84: Corporate Soul Exchange | C84: Quit Before Benefits Start | D84: Career Choice | E84: Current job | F84: 1 | G84: 0 | H84: =ROUND($G84*Settings!$B$3,0) | I84: =ROUND($G84*Settings!$B$4,0) | J84: =ROUND($G84*Settings!$B$5,0) | K84: Happiness | L84: 0.08 | M84: =ROUND($L84*Settings!$B$3,0) | N84: =ROUND($L84*Settings!$B$4,0) | O84: =ROUND($L84*Settings!$B$5,0) | Q84: 0 | R84: =ROUND($Q84*Settings!$B$3,0) | S84: =ROUND($Q84*Settings!$B$4,0) | T84: =ROUND($Q84*Settings!$B$5,0) | V84: 0 | W84: Career | X84: 0.05 | Z84: 0 | AA84: Lose job tier until rehired | AB84: Comedy reset | AC84: MVP
A85: A084 | B85: Corporate Soul Exchange | C85: Ask for Promotion | D85: Career | E85: Critical Thinking + clothes + career threshold | F85: 2 | G85: 0 | H85: =ROUND($G85*Settings!$B$3,0) | I85: =ROUND($G85*Settings!$B$4,0) | J85: =ROUND($G85*Settings!$B$5,0) | K85: Career | L85: 0.08 | M85: =ROUND($L85*Settings!$B$3,0) | N85: =ROUND($L85*Settings!$B$4,0) | O85: =ROUND($L85*Settings!$B$5,0) | P85: Money | Q85: 0.06 | R85: =ROUND($Q85*Settings!$B$3,0) | S85: =ROUND($Q85*Settings!$B$4,0) | T85: =ROUND($Q85*Settings!$B$5,0) | V85: 0 | W85: Happiness | X85: 0.025 | Z85: 0 | AA85: REMOVED — see Education_Paths and Job_Progression sheets | AB85: REMOVED IN v5. Replaced by the 30-course Education_Paths system (courses) / Job_Progression click gates (promotion). Do not implement. | AC85: REMOVED v5
A86: A085 | B86: Debtstreet Capital | C86: Open Savings Account | D86: Money | E86: Max 1 savings account per player | F86: 1 | G86: 0.1 | H86: =ROUND($G86*Settings!$B$3,0) | I86: =ROUND($G86*Settings!$B$4,0) | J86: =ROUND($G86*Settings!$B$5,0) | K86: Money | L86: 0 | M86: =ROUND($L86*Settings!$B$3,0) | N86: =ROUND($L86*Settings!$B$4,0) | O86: =ROUND($L86*Settings!$B$5,0) | Q86: 0 | R86: =ROUND($Q86*Settings!$B$3,0) | S86: =ROUND($Q86*Settings!$B$4,0) | T86: =ROUND($Q86*Settings!$B$5,0) | V86: 0 | Z86: 0 | AA86: Creates SAVINGS holding (principal 10%B). Pays +1%B every turn via the SAVINGS INTEREST card. Safe: never standing-weighted, never destroyed. Cash Out returns the full principal. | AB86: v4: no longer grants free Money on purchase. Costs a real deposit; one account maximum. | AC86: MVP
A87: A086 | B87: Debtstreet Capital | C87: Buy Bonds | D87: Investment | E87: Money available; max 1 bond holding | F87: 1 | G87: 0.15 | H87: =ROUND($G87*Settings!$B$3,0) | I87: =ROUND($G87*Settings!$B$4,0) | J87: =ROUND($G87*Settings!$B$5,0) | K87: Money | L87: 0 | M87: =ROUND($L87*Settings!$B$3,0) | N87: =ROUND($L87*Settings!$B$4,0) | O87: =ROUND($L87*Settings!$B$5,0) | Q87: 0 | R87: =ROUND($Q87*Settings!$B$3,0) | S87: =ROUND($Q87*Settings!$B$4,0) | T87: =ROUND($Q87*Settings!$B$5,0) | V87: 0 | Z87: 0 | AA87: Creates BONDS holding (principal 15%B). Pays +2%B every turn via the BOND COUPON card. Safe: never standing-weighted, never destroyed. Cash Out returns the full principal. | AB87: v4: no immediate Money gain. Payback in about 8 turns, then profit. | AC87: MVP
A88: A087 | B88: Debtstreet Capital | C88: Buy Stocks | D88: Investment | E88: Money available; max 1 stock holding | F88: 1 | G88: 0.2 | H88: =ROUND($G88*Settings!$B$3,0) | I88: =ROUND($G88*Settings!$B$4,0) | J88: =ROUND($G88*Settings!$B$5,0) | K88: Money | L88: 0 | M88: =ROUND($L88*Settings!$B$3,0) | N88: =ROUND($L88*Settings!$B$4,0) | O88: =ROUND($L88*Settings!$B$5,0) | Q88: 0 | R88: =ROUND($Q88*Settings!$B$3,0) | S88: =ROUND($Q88*Settings!$B$4,0) | T88: =ROUND($Q88*Settings!$B$5,0) | V88: 0 | Z88: 0 | AA88: Creates STOCKS holding (principal 20%B). Draws one outcome card per turn, standing-weighted (mild). Never destroyed. Cash Out returns the full principal. | AB88: v4: no immediate Money gain. Mild swings; mostly flat for 2nd/3rd place. | AC88: MVP
A89: A088 | B89: Debtstreet Capital | C89: Buy Crypto | D89: Investment | E89: Money available; max 1 crypto holding | F89: 1 | G89: 0.25 | H89: =ROUND($G89*Settings!$B$3,0) | I89: =ROUND($G89*Settings!$B$4,0) | J89: =ROUND($G89*Settings!$B$5,0) | K89: Money | L89: 0 | M89: =ROUND($L89*Settings!$B$3,0) | N89: =ROUND($L89*Settings!$B$4,0) | O89: =ROUND($L89*Settings!$B$5,0) | Q89: 0 | R89: =ROUND($Q89*Settings!$B$3,0) | S89: =ROUND($Q89*Settings!$B$4,0) | T89: =ROUND($Q89*Settings!$B$5,0) | V89: 0 | Z89: 0 | AA89: Creates CRYPTO holding (principal 25%B). Draws one outcome card per turn, heavily standing-weighted. A RUG PULL DESTROYS the holding and the principal. Cash Out returns the full principal. | AB89: v4: no immediate Money gain. High risk/high reward; the leader's trap and the trailer's comeback. | AC89: MVP
A90: A089 | B90: Debtstreet Capital | C90: Read Tiny Print | D90: Study | E90: None | F90: 1 | G90: 0 | H90: =ROUND($G90*Settings!$B$3,0) | I90: =ROUND($G90*Settings!$B$4,0) | J90: =ROUND($G90*Settings!$B$5,0) | K90: Critical Thinking | L90: 0.05 | M90: =ROUND($L90*Settings!$B$3,0) | N90: =ROUND($L90*Settings!$B$4,0) | O90: =ROUND($L90*Settings!$B$5,0) | Q90: 0 | R90: =ROUND($Q90*Settings!$B$3,0) | S90: =ROUND($Q90*Settings!$B$4,0) | T90: =ROUND($Q90*Settings!$B$5,0) | V90: 0 | Z90: 0 | AA90: Grants the INFORMED status. The next Big Loss card drawn from ANY investment is downgraded to a Small Loss, then INFORMED is consumed. Does not stack (taking it again while INFORMED is active only grants the Critical Thinking). | AB90: v4: exact effect locked. One-shot insurance against a rug pull or crash. | AC90: MVP
A91: A090 | B91: Debtstreet Capital | C91: Take Lifestyle Loan | D91: Debt | E91: None | F91: 1 | G91: 0 | H91: =ROUND($G91*Settings!$B$3,0) | I91: =ROUND($G91*Settings!$B$4,0) | J91: =ROUND($G91*Settings!$B$5,0) | K91: Money | L91: 0.15 | M91: =ROUND($L91*Settings!$B$3,0) | N91: =ROUND($L91*Settings!$B$4,0) | O91: =ROUND($L91*Settings!$B$5,0) | Q91: 0 | R91: =ROUND($Q91*Settings!$B$3,0) | S91: =ROUND($Q91*Settings!$B$4,0) | T91: =ROUND($Q91*Settings!$B$5,0) | V91: 0 | W91: Money | X91: 0.05 | Z91: 0 | AA91: Money +15%B immediately, then -5%B is deducted automatically at the start of each of the next 4 turns (total repaid 20%B). Only one loan active at a time. | AB91: v4: repayment schedule locked. Net -5%B; a genuine emergency lever, not free money. | AC91: MVP
A92: A091 | B92: Debtstreet Capital | C92: Buy Penny Stocks | D92: Bad Decision | E92: None | F92: 1 | G92: 0.06 | H92: =ROUND($G92*Settings!$B$3,0) | I92: =ROUND($G92*Settings!$B$4,0) | J92: =ROUND($G92*Settings!$B$5,0) | L92: 0 | M92: =ROUND($L92*Settings!$B$3,0) | N92: =ROUND($L92*Settings!$B$4,0) | O92: =ROUND($L92*Settings!$B$5,0) | Q92: 0 | R92: =ROUND($Q92*Settings!$B$3,0) | S92: =ROUND($Q92*Settings!$B$4,0) | T92: =ROUND($Q92*Settings!$B$5,0) | V92: 0 | W92: Money | X92: 0.08 | Y92: Critical Thinking | Z92: 0.05 | AA92: No positive effect | AB92: Pure troll option | AC92: MVP
A93: A092 | B93: Debtstreet Capital | C93: Work | D93: Work | E93: Job assigned at Corporate Soul Exchange | F93: 2 | G93: 0 | H93: =ROUND($G93*Settings!$B$3,0) | I93: =ROUND($G93*Settings!$B$4,0) | J93: =ROUND($G93*Settings!$B$5,0) | K93: From job tier | L93: 0 | M93: =ROUND($L93*Settings!$B$3,0) | N93: =ROUND($L93*Settings!$B$4,0) | O93: =ROUND($L93*Settings!$B$5,0) | P93: From job tier | Q93: 0 | R93: =ROUND($Q93*Settings!$B$3,0) | S93: =ROUND($Q93*Settings!$B$4,0) | T93: =ROUND($Q93*Settings!$B$5,0) | V93: 0 | W93: Happiness | X93: 0.02 | Y93: Enlightenment | Z93: 0.02 | AA93: One work click (2 Time Units). Money and Career come from the current job tier in Jobs_Named / Job_Progression, NOT from this row. Money is then multiplied by this building's Money Multiplier. Career is subject to the per-turn diminishing-returns rule in Settings. | AB93: v6 BUG FIX: this row used to grant Money 6%B ($6) and Career 4-6%B on top of the job tier's own pay and Career, which double-counted Career and contradicted the v5 wage table ($40-$400 per click). Both are now zero here. | AC93: MVP | AD93: Work | AH93: 1 | AI93: Money/Career now sourced from job tier; building Money Multiplier added
A94: A093 | B94: Emotional Baggage Airport | C94: Fly to Hawaii | D94: Travel | E94: Money available | F94: 3 | G94: 0.18 | H94: =ROUND($G94*Settings!$B$3,0) | I94: =ROUND($G94*Settings!$B$4,0) | J94: =ROUND($G94*Settings!$B$5,0) | K94: Happiness | L94: 0.12 | M94: =ROUND($L94*Settings!$B$3,0) | N94: =ROUND($L94*Settings!$B$4,0) | O94: =ROUND($L94*Settings!$B$5,0) | Q94: 0 | R94: =ROUND($Q94*Settings!$B$3,0) | S94: =ROUND($Q94*Settings!$B$4,0) | T94: =ROUND($Q94*Settings!$B$5,0) | V94: 0 | Z94: 0 | AA94: Counts as major relaxation | AB94: Best happiness route, costly | AC94: MVP | AD94: Relax
A95: A094 | B95: Emotional Baggage Airport | C95: Fly to Japan | D95: Travel | E95: Money available | F95: 3 | G95: 0.22 | H95: =ROUND($G95*Settings!$B$3,0) | I95: =ROUND($G95*Settings!$B$4,0) | J95: =ROUND($G95*Settings!$B$5,0) | K95: Happiness | L95: 0.1 | M95: =ROUND($L95*Settings!$B$3,0) | N95: =ROUND($L95*Settings!$B$4,0) | O95: =ROUND($L95*Settings!$B$5,0) | P95: Enlightenment | Q95: 0.05 | R95: =ROUND($Q95*Settings!$B$3,0) | S95: =ROUND($Q95*Settings!$B$4,0) | T95: =ROUND($Q95*Settings!$B$5,0) | V95: 0 | Z95: 0 | AA95: Counts as major relaxation | AB95: Happiness + enlightenment | AC95: MVP | AD95: Relax
A96: A095 | B96: Emotional Baggage Airport | C96: Fly to France | D96: Travel | E96: Money available | F96: 3 | G96: 0.2 | H96: =ROUND($G96*Settings!$B$3,0) | I96: =ROUND($G96*Settings!$B$4,0) | J96: =ROUND($G96*Settings!$B$5,0) | K96: Happiness | L96: 0.1 | M96: =ROUND($L96*Settings!$B$3,0) | N96: =ROUND($L96*Settings!$B$4,0) | O96: =ROUND($L96*Settings!$B$5,0) | P96: Coolness Factor | Q96: 0.03 | R96: =ROUND($Q96*Settings!$B$3,0) | S96: =ROUND($Q96*Settings!$B$4,0) | T96: =ROUND($Q96*Settings!$B$5,0) | V96: 0 | Z96: 0 | AA96: Counts as major relaxation | AB96: No connection bonus | AC96: MVP | AD96: Relax
A97: A096 | B97: Emotional Baggage Airport | C97: Fly to Australia | D97: Travel | E97: Money available | F97: 3 | G97: 0.25 | H97: =ROUND($G97*Settings!$B$3,0) | I97: =ROUND($G97*Settings!$B$4,0) | J97: =ROUND($G97*Settings!$B$5,0) | K97: Happiness | L97: 0.15 | M97: =ROUND($L97*Settings!$B$3,0) | N97: =ROUND($L97*Settings!$B$4,0) | O97: =ROUND($L97*Settings!$B$5,0) | Q97: 0 | R97: =ROUND($Q97*Settings!$B$3,0) | S97: =ROUND($Q97*Settings!$B$4,0) | T97: =ROUND($Q97*Settings!$B$5,0) | V97: 0 | Z97: 0 | AA97: Counts as major relaxation | AB97: Big happiness | AC97: MVP | AD97: Relax
A98: A097 | B98: Emotional Baggage Airport | C98: Long-Term Backpacking Trip | D98: Travel | E98: Money + time available | F98: 3 | G98: 0.35 | H98: =ROUND($G98*Settings!$B$3,0) | I98: =ROUND($G98*Settings!$B$4,0) | J98: =ROUND($G98*Settings!$B$5,0) | K98: Happiness | L98: 0.15 | M98: =ROUND($L98*Settings!$B$3,0) | N98: =ROUND($L98*Settings!$B$4,0) | O98: =ROUND($L98*Settings!$B$5,0) | P98: Enlightenment | Q98: 0.1 | R98: =ROUND($Q98*Settings!$B$3,0) | S98: =ROUND($Q98*Settings!$B$4,0) | T98: =ROUND($Q98*Settings!$B$5,0) | V98: 0 | Z98: 0 | AA98: Counts as major relaxation | AB98: Very expensive/time-heavy | AC98: MVP | AD98: Relax
A99: A098 | B99: Emotional Baggage Airport | C99: Complain About Missing Baggage | D99: Comedy | E99: None | F99: 1 | G99: 0 | H99: =ROUND($G99*Settings!$B$3,0) | I99: =ROUND($G99*Settings!$B$4,0) | J99: =ROUND($G99*Settings!$B$5,0) | K99: Happiness | L99: 0.025 | M99: =ROUND($L99*Settings!$B$3,0) | N99: =ROUND($L99*Settings!$B$4,0) | O99: =ROUND($L99*Settings!$B$5,0) | Q99: 0 | R99: =ROUND($Q99*Settings!$B$3,0) | S99: =ROUND($Q99*Settings!$B$4,0) | T99: =ROUND($Q99*Settings!$B$5,0) | V99: 0 | W99: Critical Thinking | X99: 0.03 | Z99: 0 | AB99: Dumb happiness | AC99: MVP
A100: A099 | B100: Emotional Baggage Airport | C100: Buy Travel Insurance | D100: Travel Prep | E100: Before travel | F100: 1 | G100: 0.04 | H100: =ROUND($G100*Settings!$B$3,0) | I100: =ROUND($G100*Settings!$B$4,0) | J100: =ROUND($G100*Settings!$B$5,0) | K100: Critical Thinking | L100: 0.03 | M100: =ROUND($L100*Settings!$B$3,0) | N100: =ROUND($L100*Settings!$B$4,0) | O100: =ROUND($L100*Settings!$B$5,0) | Q100: 0 | R100: =ROUND($Q100*Settings!$B$3,0) | S100: =ROUND($Q100*Settings!$B$4,0) | T100: =ROUND($Q100*Settings!$B$5,0) | V100: 0 | Z100: 0 | AA100: Reduces bad travel event chance | AB100: Small prep | AC100: MVP
...

Sheet Items_Mall
A1: Item_ID | B1: Shop / Group | C1: Item | D1: Slot | E1: Requirement | F1: Housing Requirement | G1: Cost %B | H1: Cost Short | I1: Cost Medium | J1: Cost Long | K1: Stat Bonus | L1: Bonus % | M1: Penalty Stat | N1: Penalty % | O1: Unlock / Effect | P1: Notes | Q1: MVP Priority | R1: Bonus Trigger (v5) | S1: Flat Bonus (Short) (v5)
A2: I001 | B2: Transportation | C2: Bus Pass | D2: Transport | E2: None | F2: Any | G2: 1 | H2: =ROUND($G2*Settings!$B$3,0) | I2: =ROUND($G2*Settings!$B$4,0) | J2: =ROUND($G2*Settings!$B$5,0) | L2: 0 | O2: Slightly reduced movement cost | P2: Entry mobility | Q2: MVP
A3: I002 | B3: Transportation | C3: Bicycle | D3: Transport | E3: None | F3: Any | G3: 7.5 | H3: =ROUND($G3*Settings!$B$3,0) | I3: =ROUND($G3*Settings!$B$4,0) | J3: =ROUND($G3*Settings!$B$5,0) | K3: Health | L3: 0.05 | O3: Faster movement + small Health benefit | P3: Good early investment; still reachable in the first third of the game | Q3: MVP
A4: I003 | B4: Transportation | C4: Car | D4: Transport | E4: None | F4: Any | G4: 20 | H4: =ROUND($G4*Settings!$B$3,0) | I4: =ROUND($G4*Settings!$B$4,0) | J4: =ROUND($G4*Settings!$B$5,0) | L4: 0 | O4: Fastest movement; no upkeep | P4: v4: major late-game purchase. Roughly a full game-third of savings on a mid job | Q4: MVP
A5: I004 | B5: Electronics/Appliances | C5: Computer | D5: Tech | E5: Desk recommended | F5: Any | G5: 10 | H5: =ROUND($G5*Settings!$B$3,0) | I5: =ROUND($G5*Settings!$B$4,0) | J5: =ROUND($G5*Settings!$B$5,0) | K5: Critical Thinking | L5: 0.04 | O5: Required for better jobs / work from home | P5: v4: core career item, now a real mid-game goal | Q5: MVP
A6: I005 | B6: Electronics/Appliances | C6: Mobile Phone | D6: Tech | E6: None | F6: Any | G6: 5 | H6: =ROUND($G6*Settings!$B$3,0) | I6: =ROUND($G6*Settings!$B$4,0) | J6: =ROUND($G6*Settings!$B$5,0) | K6: Career | L6: 0.03 | O6: Job calls + social events | P6: Personal item, no housing needed | Q6: MVP
A7: I006 | B7: Electronics/Appliances | C7: Camera | D7: Tech | E7: None | F7: Any | G7: 8 | H7: =ROUND($G7*Settings!$B$3,0) | I7: =ROUND($G7*Settings!$B$4,0) | J7: =ROUND($G7*Settings!$B$5,0) | K7: Connection | L7: 0.04 | O7: Creator/social route | P7: Creator/social route | Q7: MVP
A8: I007 | B8: Electronics/Appliances | C8: TV | D8: Tech | E8: Luxury apartment | F8: Luxury only | G8: 5 | H8: =ROUND($G8*Settings!$B$3,0) | I8: =ROUND($G8*Settings!$B$4,0) | J8: =ROUND($G8*Settings!$B$5,0) | K8: Happiness | L8: 0.04 | O8: Home happiness bonus | P8: v4: hard-gated. No room for a TV in low-cost housing | Q8: MVP
A9: I008 | B9: Electronics/Appliances | C9: Blu-ray | D9: Tech | E9: TV owned | F9: Luxury only | G9: 3 | H9: =ROUND($G9*Settings!$B$3,0) | I9: =ROUND($G9*Settings!$B$4,0) | J9: =ROUND($G9*Settings!$B$5,0) | K9: Happiness | L9: 0.03 | O9: Extra entertainment | P9: v4: hard-gated behind TV + luxury | Q9: MVP
A10: I009 | B10: Electronics/Appliances | C10: E-reader | D10: Tech | E10: None | F10: Any | G10: 1 | H10: =ROUND($G10*Settings!$B$3,0) | I10: =ROUND($G10*Settings!$B$4,0) | J10: =ROUND($G10*Settings!$B$5,0) | K10: Critical Thinking | L10: 0.05 | O10: Reading bonus | P10: Personal item | Q10: MVP
A11: I010 | B11: Electronics/Appliances | C11: Stereo | D11: Tech | E11: Luxury apartment | F11: Luxury only | G11: 2 | H11: =ROUND($G11*Settings!$B$3,0) | I11: =ROUND($G11*Settings!$B$4,0) | J11: =ROUND($G11*Settings!$B$5,0) | K11: Happiness | L11: 0.04 | O11: Home entertainment | P11: v4: hard-gated | Q11: MVP
A12: I011 | B12: Electronics/Appliances | C12: Watch | D12: Accessory | E12: None | F12: Any | G12: 0.25 | H12: =ROUND($G12*Settings!$B$3,0) | I12: =ROUND($G12*Settings!$B$4,0) | J12: =ROUND($G12*Settings!$B$5,0) | K12: Coolness Factor | L12: 0.05 | O12: Coolness accessory | P12: Coolness accessory | Q12: MVP
A13: I012 | B13: Electronics/Appliances | C13: Fridge | D13: Appliance | E13: Any housing | F13: Low Cost OK | G13: 9.5 | H13: =ROUND($G13*Settings!$B$3,0) | I13: =ROUND($G13*Settings!$B$4,0) | J13: =ROUND($G13*Settings!$B$5,0) | L13: 0 | O13: REQUIRED to store 2-week and 4-week groceries from Air One. Without a fridge those bulk options are unavailable and any bulk food already held spoils. Also grants a one-time Health +3 on purchase. | P13: v4: food engine, priced as a mid-game unlock | Q13: MVP | R13: ONE-TIME on purchase | S13: Health +3
A14: I013 | B14: Electronics/Appliances | C14: Stove | D14: Appliance | E14: Any housing | F14: Low Cost OK | G14: 6.5 | H14: =ROUND($G14*Settings!$B$3,0) | I14: =ROUND($G14*Settings!$B$4,0) | J14: =ROUND($G14*Settings!$B$5,0) | L14: 0 | O14: Unlocks meal prep | P14: v4: food engine | Q14: MVP | R14: Each relax action in your home | S14: Health +1
A15: I014 | B15: Electronics/Appliances | C15: Vacuum | D15: Appliance | E15: Any housing | F15: Low Cost OK | G15: 2.5 | H15: =ROUND($G15*Settings!$B$3,0) | I15: =ROUND($G15*Settings!$B$4,0) | J15: =ROUND($G15*Settings!$B$5,0) | L15: 0 | O15: Clean home health bonus | Q15: MVP | R15: ONE-TIME on purchase | S15: Health +3
A16: I015 | B16: Electronics/Appliances | C16: Cold Plunge | D16: Appliance | E16: Luxury apartment | F16: Luxury only | G16: 2 | H16: =ROUND($G16*Settings!$B$3,0) | I16: =ROUND($G16*Settings!$B$4,0) | J16: =ROUND($G16*Settings!$B$5,0) | L16: 0 | O16: Premium health item | P16: Premium health item | Q16: MVP | R16: Each exercise action in your home | S16: Health +1
A17: I016 | B17: Electronics/Appliances | C17: Hot Tub | D17: Appliance | E17: Luxury apartment | F17: Luxury only | G17: 8.5 | H17: =ROUND($G17*Settings!$B$3,0) | I17: =ROUND($G17*Settings!$B$4,0) | J17: =ROUND($G17*Settings!$B$5,0) | L17: 0 | O17: Premium happiness + hosting flavor | P17: Premium happiness + hosting | Q17: MVP | R17: Each relax action in your home | S17: Happiness +1
A18: I017 | B18: Furniture | C18: Lumpy Bed | D18: Bed | E18: Any housing | F18: Low Cost OK | G18: 0.5 | H18: =ROUND($G18*Settings!$B$3,0) | I18: =ROUND($G18*Settings!$B$4,0) | J18: =ROUND($G18*Settings!$B$5,0) | L18: 0 | O18: Small sleep bonus | P18: Cheap starter bed | Q18: MVP | R18: Each sleep action in your home | S18: Health +1
A19: I018 | B19: Furniture | C19: Nice Bed | D19: Bed | E19: Any housing | F19: Low Cost OK | G19: 5 | H19: =ROUND($G19*Settings!$B$3,0) | I19: =ROUND($G19*Settings!$B$4,0) | J19: =ROUND($G19*Settings!$B$5,0) | L19: 0 | O19: Medium sleep bonus | P19: v4: mid-game sleep upgrade | Q19: MVP | R19: Each sleep action in your home | S19: Health +2
A20: I019 | B20: Furniture | C20: Premium Bed | D20: Bed | E20: Luxury apartment | F20: Luxury only | G20: 9 | H20: =ROUND($G20*Settings!$B$3,0) | I20: =ROUND($G20*Settings!$B$4,0) | J20: =ROUND($G20*Settings!$B$5,0) | L20: 0 | O20: Large sleep bonus | P20: v4: hard-gated (was only 'recommended') | Q20: MVP | R20: Each sleep action in your home | S20: Health +3
A21: I020 | B21: Furniture | C21: Couch | D21: Furniture | E21: Luxury apartment | F21: Luxury only | G21: 6.5 | H21: =ROUND($G21*Settings!$B$3,0) | I21: =ROUND($G21*Settings!$B$4,0) | J21: =ROUND($G21*Settings!$B$5,0) | K21: Happiness | L21: 0.04 | O21: Relaxing at home bonus | P21: v4: hard-gated. No space in a bunk room | Q21: MVP
A22: I021 | B22: Furniture | C22: Bookshelf | D22: Furniture | E22: Any housing | F22: Low Cost OK | G22: 0.8 | H22: =ROUND($G22*Settings!$B$3,0) | I22: =ROUND($G22*Settings!$B$4,0) | J22: =ROUND($G22*Settings!$B$5,0) | L22: 0 | O22: Study/home critical thinking bonus | Q22: MVP | R22: Each relax action in your home | S22: Critical Thinking +1
A23: I022 | B23: Furniture | C23: Plants | D23: Furniture | E23: Any housing | F23: Low Cost OK | G23: 0.2 | H23: =ROUND($G23*Settings!$B$3,0) | I23: =ROUND($G23*Settings!$B$4,0) | J23: =ROUND($G23*Settings!$B$5,0) | L23: 0 | O23: Home wellness bonus | Q23: MVP | R23: Each relax action in your home | S23: Enlightenment +1
A24: I023 | B24: Furniture | C24: Desk | D24: Work Setup | E24: Any housing | F24: Low Cost OK | G24: 3.5 | H24: =ROUND($G24*Settings!$B$3,0) | I24: =ROUND($G24*Settings!$B$4,0) | J24: =ROUND($G24*Settings!$B$5,0) | L24: 0 | O24: Required for better work-from-home efficiency | P24: Needed for work-from-home | Q24: MVP | R24: Each work-from-home action | S24: Critical Thinking +1
A25: I024 | B25: Furniture | C25: Ergonomic Chair | D25: Work Setup | E25: Luxury apartment | F25: Luxury only | G25: 6 | H25: =ROUND($G25*Settings!$B$3,0) | I25: =ROUND($G25*Settings!$B$4,0) | J25: =ROUND($G25*Settings!$B$5,0) | L25: 0 | O25: Health + work comfort | P25: v4: hard-gated | Q25: MVP | R25: Each work-from-home action | S25: Health +1
A26: I025 | B26: Furniture | C26: Pet Bed | D26: Pet Item | E26: Own pet | F26: Low Cost OK | G26: 1.5 | H26: =ROUND($G26*Settings!$B$3,0) | I26: =ROUND($G26*Settings!$B$4,0) | J26: =ROUND($G26*Settings!$B$5,0) | L26: 0 | O26: Pet health support | Q26: MVP | R26: Each play-with-pet action in your home | S26: Pet Health +1
A27: I026 | B27: Furniture | C27: Pet Toys | D27: Pet Item | E27: Own pet | F27: Low Cost OK | G27: 0.35 | H27: =ROUND($G27*Settings!$B$3,0) | I27: =ROUND($G27*Settings!$B$4,0) | J27: =ROUND($G27*Settings!$B$5,0) | L27: 0 | O27: Pet happiness support | Q27: MVP | R27: Each play-with-pet action in your home | S27: Pet Happiness +1
A28: I027 | B28: Furniture | C28: Dining Table | D28: Furniture | E28: Luxury apartment | F28: Luxury only | G28: 4.5 | H28: =ROUND($G28*Settings!$B$3,0) | I28: =ROUND($G28*Settings!$B$4,0) | J28: =ROUND($G28*Settings!$B$5,0) | L28: 0 | O28: Hosting friends support | P28: v4: hard-gated. Hosting requires a dining room | Q28: MVP | R28: Each relax action in your home | S28: Health +1
A29: I028 | B29: Furniture | C29: Mirror | D29: Furniture | E29: Any housing | F29: Low Cost OK | G29: 0.9 | H29: =ROUND($G29*Settings!$B$3,0) | I29: =ROUND($G29*Settings!$B$4,0) | J29: =ROUND($G29*Settings!$B$5,0) | L29: 0 | O29: Flex/check outfit | Q29: MVP | R29: Each relax action in your home | S29: Coolness Factor +1
A30: I029 | B30: Clothing | C30: Casual Clothes | D30: Outfit | E30: None | F30: Any | G30: 0.5 | H30: =ROUND($G30*Settings!$B$3,0) | I30: =ROUND($G30*Settings!$B$4,0) | J30: =ROUND($G30*Settings!$B$5,0) | L30: 0 | O30: Required for low-tier jobs | P30: UNCHANGED ON PURPOSE: must stay affordable after the 30%B homeless cheque alongside 20%B low rent | Q30: MVP
A31: I030 | B31: Clothing | C31: Smart Clothes | D31: Outfit | E31: Casual clothes | F31: Any | G31: 4 | H31: =ROUND($G31*Settings!$B$3,0) | I31: =ROUND($G31*Settings!$B$4,0) | J31: =ROUND($G31*Settings!$B$5,0) | K31: Career | L31: 0.03 | O31: Required for mid-tier jobs | P31: v4: mid-tier job gate | Q31: MVP
A32: I031 | B32: Clothing | C32: Business Clothes | D32: Outfit | E32: Smart clothes | F32: Any | G32: 5 | H32: =ROUND($G32*Settings!$B$3,0) | I32: =ROUND($G32*Settings!$B$4,0) | J32: =ROUND($G32*Settings!$B$5,0) | K32: Career | L32: 0.05 | O32: Required for high/elite jobs | P32: v4: high/elite job gate, now a real investment | Q32: MVP
A33: I032 | B33: Clothing | C33: Dressy Clothes | D33: Outfit | E33: None | F33: Any | G33: 3 | H33: =ROUND($G33*Settings!$B$3,0) | I33: =ROUND($G33*Settings!$B$4,0) | J33: =ROUND($G33*Settings!$B$5,0) | K33: Coolness Factor | L33: 0.04 | O33: Required for club/VIP actions | P33: v4: club/VIP gate | Q33: MVP
A34: I033 | B34: Clothing | C34: Sunglasses | D34: Accessory | E34: None | F34: Any | G34: 1 | H34: =ROUND($G34*Settings!$B$3,0) | I34: =ROUND($G34*Settings!$B$4,0) | J34: =ROUND($G34*Settings!$B$5,0) | K34: Coolness Factor | L34: 0.05 | O34: Coolness accessory | Q34: MVP
A35: I034 | B35: Clothing | C35: Earrings | D35: Accessory | E35: None | F35: Any | G35: 0.14 | H35: =ROUND($G35*Settings!$B$3,0) | I35: =ROUND($G35*Settings!$B$4,0) | J35: =ROUND($G35*Settings!$B$5,0) | K35: Coolness Factor | L35: 0.03 | O35: Coolness accessory | Q35: MVP
A36: I035 | B36: Clothing | C36: Bracelet | D36: Accessory | E36: None | F36: Any | G36: 0.14 | H36: =ROUND($G36*Settings!$B$3,0) | I36: =ROUND($G36*Settings!$B$4,0) | J36: =ROUND($G36*Settings!$B$5,0) | K36: Coolness Factor | L36: 0.03 | O36: Coolness accessory | Q36: MVP
A37: I036 | B37: Clothing | C37: Rings | D37: Accessory | E37: None | F37: Any | G37: 0.2 | H37: =ROUND($G37*Settings!$B$3,0) | I37: =ROUND($G37*Settings!$B$4,0) | J37: =ROUND($G37*Settings!$B$5,0) | K37: Coolness Factor | L37: 0.04 | O37: Coolness accessory | Q37: MVP
A38: I037 | B38: Clothing | C38: Dress Shoes | D38: Footwear | E38: None | F38: Any | G38: 2 | H38: =ROUND($G38*Settings!$B$3,0) | I38: =ROUND($G38*Settings!$B$4,0) | J38: =ROUND($G38*Settings!$B$5,0) | K38: Coolness Factor | L38: 0.04 | O38: Coolness footwear | Q38: MVP
A39: I038 | B39: Clothing | C39: High Heels | D39: Footwear | E39: None | F39: Any | G39: 0.2 | H39: =ROUND($G39*Settings!$B$3,0) | I39: =ROUND($G39*Settings!$B$4,0) | J39: =ROUND($G39*Settings!$B$5,0) | K39: Coolness Factor | L39: 0.04 | O39: Coolness footwear | Q39: MVP
A40: I039 | B40: Clothing | C40: Crocodile Sandals | D40: Footwear | E40: None | F40: Any | G40: 0.1 | H40: =ROUND($G40*Settings!$B$3,0) | I40: =ROUND($G40*Settings!$B$4,0) | J40: =ROUND($G40*Settings!$B$5,0) | K40: Happiness | L40: 0.03 | N40: 0 | O40: Comfort meme item | P40: Comfort meme item | v5: stat penalty removed | Q40: MVP
A41: I040 | B41: Clothing | C41: Durag | D41: Accessory | E41: None | F41: Any | G41: 0.12 | H41: =ROUND($G41*Settings!$B$3,0) | I41: =ROUND($G41*Settings!$B$4,0) | J41: =ROUND($G41*Settings!$B$5,0) | K41: Coolness Factor | L41: 0.04 | N41: 0 | O41: Playtest-sensitive | P41: Playtest-sensitive; review feedback | v5: stat penalty removed | Q41: MVP
A42: I041 | B42: Clothing | C42: Cap | D42: Accessory | E42: None | F42: Any | G42: 0.1 | H42: =ROUND($G42*Settings!$B$3,0) | I42: =ROUND($G42*Settings!$B$4,0) | J42: =ROUND($G42*Settings!$B$5,0) | K42: Coolness Factor | L42: 0.025 | O42: Cheap coolness accessory | P42: Cheap coolness accessory | Q42: MVP
A43: I042 | B43: Furniture | C43: Fancy Dinnerware | D43: Furniture | E43: Luxury apartment | F43: Luxury only | G43: 2.5 | H43: =ROUND($G43*Settings!$B$3,0) | I43: =ROUND($G43*Settings!$B$4,0) | J43: =ROUND($G43*Settings!$B$5,0) | L43: 0 | O43: REQUIRED for the Host Friends action at Luxury Apartments. Without it there is nothing to serve dinner on and the action is unavailable. | P43: New in v6. Home fixture: exempt from the best-item-per-slot rule. | Q43: MVP | R43: Each Host Friends action at home | S43: Coolness Factor +1
A45: HOUSING GATE RULE (new in v4): 'Any' = buyable regardless of housing (personal items you carry). 'Low Cost OK' = requires housing, works in Low Cost Housing or Luxury. 'Luxury only' = CANNOT be bought or used while living in Low Cost Housing. If a player owning a Luxury-only item moves back to Low Cost Housing or becomes homeless, the item is placed in storage: it stops providing its bonus until they return to Luxury housing. It is not lost.
A46: PRICING RULE (new in v4): every mall price resolves against B, not the stat cap. Prices were raised roughly 2-3x versus v3 so that electronics, appliances, and furniture are mid-game goals rather than turn-2 purchases. Recurring costs (food, rent, pet upkeep) were deliberately NOT raised, so the change slows down accumulation without making survival harder.
A48: V5 PRICING: all prices are absolute dollars at the Short baseline (B=100) and scale with B (Medium x2.5, Long x3.5). Prices were raised 5-25x for pacing, and job pay, rent and food were rebuilt to match — see the money economy block in Settings.
A49: V5 BONUSES: flat trigger bonuses are FIXED POINT VALUES, not percentages. They fire every time their trigger action is taken at home. Items with a trigger no longer carry a percentage bonus. All mall stat penalties are removed.
A50: V5 HOME FIXTURES EXEMPTION: bookshelf, plants, dining table, mirror, stove, hot tub, couch, desk, ergonomic chair, cold plunge, beds and pet items are HOME FIXTURES. The best-item-per-slot rule does NOT apply to them — a player owns each one or does not, and every owned fixture fires its own trigger. Only one bed counts (the best owned).
A52: V6 ITEM GATES: four Luxury Apartment actions now require a purchase. Sleep in Fancy Bed requires any bed (Lumpy, Nice or Premium). Take Luxury Bath requires the Hot Tub. Relax in Your Suite requires the Couch. Host Friends requires the new Fancy Dinnerware (I042). An empty luxury apartment is now an empty room.
A53: V6 UI RULE: an action whose item requirement is unmet must still be listed in the menu, greyed out, with the missing item named on the row ("Needs: Hot Tub - $850 at the Mall"). Hiding it is what makes a menu look broken.
A54: V6 UNIT NOTE: the Cost column is a MULTIPLE of B, not a percentage. 0.5 = $50 at the Short baseline, 1 = $100, 20 = $2,000. Reading it as a percentage makes a car cost $20.

Sheet Jobs_Named
A1: CANONICAL JOB LIST — RE-ORDERED IN v6. Rows are now sorted by TIER (Low, Low+, Mid, Mid+, High, Max) and then alphabetically by building, so the job board reads as one ladder and a player can see at a glance which jobs their current clicks and education make available. It is NOT grouped by building any more. v6 also fills in the missing Low+ and Mid+ rungs (previously Low+ had exactly one job in the whole game) and normalises the stray 'Max+' tier on Wolf of Debtstreet to Max. Pay = tier pay x the building's Money Multiplier (Building_Map sheet). Career gain is now set by tier and is the ONLY source of Career from a work click — see the Career Patch v6 block in Settings. Eligibility requires BOTH the tier's work-click count AND its education path; clothing requirements apply on top.
A3: Tier Rank | B3: Tier | C3: Building | D3: Job Name | E3: Base Pay $ (Short, before multiplier) | F3: Money Multiplier (Building_Map) | G3: Pay per click $ (Short, v6) | H3: Career Gain per click (v6) | I3: Extra Effect | J3: Item / Stat Requirement | K3: Education required | L3: Work clicks required
A4: 1 | B4: Low | C4: Air One Supermarket | D4: Cashier | E4: 40 | F4: 1.1 | G4: =ROUND(E4*F4,0) | H4: 2 | I4: +1 Health | J4: Casual Clothes | K4: No education | L4: Entry
A5: 1 | B5: Low | C5: Bad Decisions Club | D5: Coat Check Staff | E5: 40 | F5: 1.2 | G5: =ROUND(E5*F5,0) | H5: 2 | I5: +1 Connection, -1 Health | J5: Casual Clothes, Coolness 10+ | K5: No education | L5: Entry
A6: 1 | B6: Low | C6: Bro Science Gym | D6: Front Desk Staff | E6: 40 | F6: 1.2 | G6: =ROUND(E6*F6,0) | H6: 2 | I6: +1 Health | J6: Casual Clothes | K6: No education | L6: Entry
A7: 1 | B7: Low | C7: Corporate Soul Exchange | D7: Warehouse Worker | E7: 40 | F7: 1 | G7: =ROUND(E7*F7,0) | H7: 2 | I7: -2 Health, -2 Happiness | J7: Casual Clothes | K7: No education | L7: Entry
A8: 1 | B8: Low | C8: Debtstreet Capital | D8: Teller | E8: 40 | F8: 1 | G8: =ROUND(E8*F8,0) | H8: 2 | I8: +1 Critical Thinking | J8: Casual Clothes | K8: No education | L8: Entry
A9: 1 | B9: Low | C9: Emotional Baggage Airport | D9: Gate Agent | E9: 40 | F9: 1.35 | G9: =ROUND(E9*F9,0) | H9: 2 | I9: -1 Happiness | J9: Casual Clothes | K9: No education | L9: Entry
A10: 1 | B10: Low | C10: Ethical Pet Shop | D10: Pet Poop Cleaner | E10: 40 | F10: 1.2 | G10: =ROUND(E10*F10,0) | H10: 2 | I10: +2 Pet Happiness | J10: Casual Clothes | K10: No education | L10: Entry
A11: 1 | B11: Low | C11: High IQ University | D11: Janitor | E11: 40 | F11: 1.1 | G11: =ROUND(E11*F11,0) | H11: 2 | I11: +1 Health | J11: Casual Clothes | K11: No education | L11: Entry
A12: 1 | B12: Low | C12: Mall | D12: Cashier | E12: 40 | F12: 1 | G12: =ROUND(E12*F12,0) | H12: 2 | I12: +1 Coolness | J12: Casual Clothes | K12: No education | L12: Entry
A13: 1 | B13: Low | C13: Re-Education Temple | D13: Chant Circle Assistant | E13: 40 | F13: 1.35 | G13: =ROUND(E13*F13,0) | H13: 2 | I13: +2 Enlightenment | J13: Casual Clothes | K13: No education | L13: Entry
A14: 1 | B14: Low | C14: Regret Burger | D14: Cook | E14: 40 | F14: 1.1 | G14: =ROUND(E14*F14,0) | H14: 2 | I14: -2 Health, -1 Happiness | J14: Casual Clothes | K14: No education | L14: Entry
A15: 2 | B15: Low+ | C15: Air One Supermarket | D15: Produce Mister | E15: 65 | F15: 1.1 | G15: =ROUND(E15*F15,0) | H15: 2 | I15: +1 Health | J15: Casual Clothes | K15: Path 1 complete | L15: 10 Low clicks
... A70: 6 | B70: Max | C70: Re-Education Temple | D70: The Messiah | E70: 400 | F70: 1.35 | G70: =ROUND(E70*F70,0) | H70: 5 | I70: +7 Enlightenment, +2 Connection, -5 Critical Thinking | J70: Business Clothes, Enlightenment 90+, Career 70+ | K70: Path 5 complete | L70: 40 High clicks
A72: NEW IN v6 (highlighted rows) | B72: Twenty jobs were added to fill the empty Low+ and Mid+ rungs. In v5 the Low+ tier contained exactly one job in the entire game (Regret Burger Cashier) and Mid+ contained three, so completing Path 1 or Path 3 unlocked almost nothing. These rows can be deleted without breaking any other system.
A73: Sort order | B73: Tier Rank 1-6 then building name. Keep this order in the job board UI. Group headers read LOW / LOW+ / MID / MID+ / HIGH / MAX.
A74: Job board UI | B74: Show all six tier groups at all times. Locked tiers stay visible and greyed, with the exact reason on the row: "Needs Path 2 (College Diploma)" or "Needs 4 more Low+ clicks" or "Needs Smart Clothes". Never hide a job the player cannot take yet — seeing the ladder is the point of the re-order.
A75: Pay | B75: Pay per click = ROUND(tier pay x building Money Multiplier). Tier pay scales with B (Medium x2.5, Long x3.5); the multiplier does not scale.
A76: Career | B76: Career gain per work click comes from this sheet ONLY. The Work rows in Actions_Master no longer grant Career or Money — that was a double-count. Career gain is then subject to the per-turn diminishing-returns rule in Settings.

Sheet Pets
A1: Pet Type | B1: Main Bonus | C1: Upkeep Bonus | D1: Pet Bonus Rule | E1: Suggested Use | F1: Notes
A2: ENFP Pet | B2: Happiness | C2: Coolness Factor | D2: +10% if neutral; +5% if stacking strength; halves weakness penalty | E2: Covers fun/coolness routes
A3: ESTP Pet | B3: Health | C3: Money | D3: +10% if neutral; +5% if stacking strength; halves weakness penalty | E3: Good for ENFP/ENFJ health-money weakness
A4: ENTP Pet | B4: Health | C4: Critical Thinking | D4: +10% if neutral; +5% if stacking strength; halves weakness penalty | E4: Health/logic helper
A5: ESFP Pet | B5: Happiness | C5: Coolness Factor | D5: +10% if neutral; +5% if stacking strength; halves weakness penalty | E5: Fun/coolness route
A6: ENFJ Pet | B6: Connection | C6: Enlightenment | D6: +10% if neutral; +5% if stacking strength; halves weakness penalty | E6: Social/spiritual helper
A7: ESFJ Pet | B7: Connection | C7: Coolness Factor | D7: +10% if neutral; +5% if stacking strength; halves weakness penalty | E7: Social/coolness helper
A8: ENTJ Pet | B8: Career | C8: Money | D8: +10% if neutral; +5% if stacking strength; halves weakness penalty | E8: Engine pet; watch snowball | F8: Career/Money caps apply
A9: ESTJ Pet | B9: Career | C9: Money | D9: +10% if neutral; +5% if stacking strength; halves weakness penalty | E9: Engine pet; watch snowball | F9: Career/Money caps apply
A10: INTJ Pet | B10: Career | C10: Critical Thinking | D10: +10% if neutral; +5% if stacking strength; halves weakness penalty | E10: Career/logic helper
A11: ISTJ Pet | B11: Career | C11: Money | D11: +10% if neutral; +5% if stacking strength; halves weakness penalty | E11: Engine pet; watch snowball | F11: Career/Money caps apply
A12: ISFJ Pet | B12: Connection | C12: Enlightenment | D12: +10% if neutral; +5% if stacking strength; halves weakness penalty | E12: Social/spiritual helper
A13: INFJ Pet | B13: Connection | C13: Enlightenment | D13: +10% if neutral; +5% if stacking strength; halves weakness penalty | E13: Social/spiritual helper
A14: INFP Pet | B14: Happiness | C14: Enlightenment | D14: +10% if neutral; +5% if stacking strength; halves weakness penalty | E14: Happiness/enlightenment helper
A15: ISFP Pet | B15: Happiness | C15: Coolness Factor | D15: +10% if neutral; +5% if stacking strength; halves weakness penalty | E15: Fun/coolness helper
A16: ISTP Pet | B16: Health | C16: Critical Thinking | D16: +10% if neutral; +5% if stacking strength; halves weakness penalty | E16: Health/logic helper
A17: INTP Pet | B17: Health | C17: Critical Thinking | D17: +10% if neutral; +5% if stacking strength; halves weakness penalty | E17: Health/logic helper
A18: Pet Care Rule | B18: Pet Health | C18: Pet Happiness | D18: Fed/Healthy → Hungry → Sick → Critical → Dead | E18: Warnings occur as Pet Health drops | F18: If pet dies, player Happiness drops to 0
A20: FEEDING & DEATH RULES (v3 — replaces the old Healthy/Hungry/Sick/Critical/Dead states)
A21: Consecutive missed feedings | B21: Result | C21: Card
A22: 1 | B22: Pet is Sad: Pet Happiness -Standard (5%T) | C22: S03 SAD PET
A23: 2 | B23: Pet is Starving: Pet Health -Strong (8%T), Pet Happiness -Strong (8%T). Final warning. | C23: S04 STARVING PET
A24: 3 | B24: Pet dies. Tombstone appears in the player's housing (permanent). Owner Happiness set to 0. Re-adoption allowed; pet stats restart. | C24: S05 YOUR PET DIED
A25: Reset | B25: Feeding the pet on any turn resets the missed-feeding counter to 0. | C25: —

Sheet Jobs_Tiers
A1: Generic 4-tier job math kept for reference / fallback if Jobs_Named is too much for the first build. %T-based like all other actions.
A3: Tier | B3: Requirement | C3: Time Units | D3: Money Gain %T | E3: Career Gain %T | F3: Health Penalty %T | G3: Happiness Penalty %T | H3: Notes
A4: Low | B4: Casual clothes | C4: 2 | D4: 0.08 | E4: 0.05 | F4: 0.02 | G4: 0.02 | H4: Entry work; available early
A5: Mid | B5: Smart clothes + Undergrad OR Critical Thinking threshold | C5: 2 | D5: 0.12 | E5: 0.07 | F5: 0.03 | G5: 0.03 | H5: First real money jump
A6: High | B6: Business clothes + Master's OR high Critical Thinking + computer | C6: 2 | D6: 0.18 | E6: 0.09 | F6: 0.04 | G6: 0.04 | H6: Strong but burns Health/Happiness
A7: Elite | B7: Business clothes + high Career/Critical Thinking + computer + premium reqs | C7: 2 | D7: 0.25 | E7: 0.12 | F7: 0.06 | G7: 0.06 | H7: Late-game engine; balance carefully

Sheet Audio_Music
A1: Building / Location | B1: Music File | C1: Trigger / Behaviour
A2: Overmap (default) | B2: PP-Overmap.mp3 | C2: Default looping background music on the world map.
A3: Overmap - Rent is Due | B3: PP-OverMapRentisDue.mp3 | C3: Replaces PP-Overmap.mp3 on the world map during every rent-due turn (turn 4, 8, 12, ... matching the 4-turn rent interval). Overrides the default track; reverts once rent is resolved / the rent turn ends.
A4: Air One Supermarket | B4: PP-AirOneSuperMarket.mp3 | C4: Plays on entering/interacting with the building.
A5: Corporate Soul Exchange Office | B5: PP-CorporateSoulExchangeOffice.mp3 | C5: Plays on entering/interacting with the building.
A6: High IQ University | B6: PP-HighIQUniversity.mp3 | C6: Plays on entering/interacting with the building.
A7: Ethical Pet Shop | B7: PP-EthicalPetShop.mp3 | C7: Plays on entering/interacting with the building.
A8: Regret Burger | B8: PP-RegretBurger.mp3 | C8: Plays on entering/interacting with the building.
A9: Bro Science Gym | B9: PP-BroScienceGym.mp3 | C9: Plays on entering/interacting with the building.
A10: Park | B10: PP-Park.mp3 | C10: Plays on entering/interacting with the building.
A11: Emotional Baggage Airport | B11: PP-EmotionalBaggageAirport.mp3 | C11: Plays on entering/interacting with the building.
A12: Debt Street Capital | B12: PP-DebtStreetCapital.mp3 | C12: Plays on entering/interacting with the building.
... A19: Rule | B19: Music Mode setting | C19: Settings screen offers Music Mode: 'Full' (overmap + building tracks, default) or 'Overmap Only' (building tracks disabled; overmap/rent-due tracks keep playing everywhere).

Sheet Audio_SFX
A1: Action / Event | B1: Sound File | C1: Type | D1: Behaviour
A2: Walking (player movement on foot) | B2: PP-Walking.wav | C2: Loop while moving | D2: Plays only when transport mode = Walking / Bus Pass. Stops immediately when movement ends or transport changes.
A3: Bicycle bell (riding bicycle) | B3: PP-BicycleBell.mp3 | C3: One-shot on move start | D3: Plays only when transport mode = Bicycle. Walking SFX is muted while Bicycle is the active transport.
A4: Car acceleration (driving) | B4: PP-CarAcceleration.mp3 | C4: One-shot on move start | D4: Plays only when transport mode = Car. Walking SFX is muted while Car is the active transport.
A5: Menu button clicked (UI) | B5: PP-MenuButtonClicked.wav | C5: One-shot | D5: All UI buttons across all screens (start, setup, settings, in-game menus).
A6: Eating fast food | B6: PP-EatingFastFood.mp3 | C6: One-shot | D6: Any Regret Burger food action; optionally reuse for other eat actions in the MVP.
A7: Money transaction | B7: PP-Money.mp3 | C7: One-shot | D7: Plays on BOTH earning and spending (single transaction cue for the MVP). Split into separate earn/spend sounds post-MVP if desired.
A9: Rule | B9: Movement SFX are mutually exclusive | D9: Only the SFX for the currently active transport slot item plays; switching transport silences the previous movement sound.
A10: Rule | B10: Volume routing | D10: All SFX route through the SFX Volume slider; all music routes through the Music Volume slider; both are children of Master Volume.

Sheet Cards
A1: WEEKEND UPDATE CARD SYSTEM. Cards appear stacked at the start of a player's turn (before the turn timer starts) and report what happened 'over the weekend'. Order shown: status cards, then investment outcomes (one per held asset), then exactly 1 event card. Effects use the standard gain tiers (Tiny 2.5%T, Standard 5%T, Strong 8%T, Premium 12%T). If a drawn event card's requirement is not met, redraw.
A3: STANDING & DRAW WEIGHTS
A4: Standing is computed at the start of each player's turn using the live provisional score (final score formula). Ties break by Money, then turn order. 2-player games: leader uses 1st-place weights, the other uses last-place weights. 3-player: 1st / middle / last.
A5: Standing | B5: Major Positive | C5: Minor Positive | D5: Minor Negative | E5: Major Negative
A6: Last place | B6: 0.35 | C6: 0.35 | D6: 0.2 | E6: 0.1
A7: 2nd / 3rd place | B7: 0 | C7: 0.5 | D7: 0.5 | E7: 0
A8: 1st place | B8: 0.1 | C8: 0.2 | D8: 0.35 | E8: 0.35
A10: INVESTMENT RESOLUTION ODDS (drawn automatically per held asset, standing-weighted)
A11: Asset | B11: Standing | C11: Big Gain | D11: Small Gain | E11: Small Loss | F11: Big Loss | G11: Card IDs used
A12: Crypto | B12: Last place | C12: 45% | D12: 30% | E12: 20% | F12: 5% (destroys holding) | G12: I01 / I03 / I02
A13: Crypto | B13: 2nd / 3rd | C13: 25% | D13: 25% | E13: 25% | F13: 25% (destroys holding) | G13: I01 / I03 / I02
A14: Crypto | B14: 1st place | C14: 5% | D14: 20% | E14: 30% | F14: 45% (destroys holding) | G14: I01 / I03 / I02
A15: Stocks | B15: Last place | C15: 20% | D15: 35% | E15: 15% | F15: 5% (flat 25%) | G15: I04 / I06 / I09 / I05 / I10
A16: Stocks | B16: 2nd / 3rd | C16: 5% | D16: 20% | E16: 20% | F16: 5% (flat 50%) | G16: I04 / I06 / I09 / I05 / I10
A17: Stocks | B17: 1st place | C17: 5% | D17: 15% | E17: 35% | F17: 20% (flat 25%) | G17: I04 / I06 / I09 / I05 / I10
A18: Bonds | B18: Any | C18: — | D18: 100% (+2%B) | E18: — | F18: — | G18: I07 safe: never standing-weighted
A19: Savings | B19: Any | C19: — | D19: 100% (+1%B) | E19: — | F19: — | G19: I08 safe: never standing-weighted
A20: Crypto is deliberately extreme (the leader's trap, the trailer's comeback); Stocks are deliberately mild, and mostly FLAT for 2nd/3rd place so mid-table players are not swung around by the market. Bonds and Savings are always safe so the leader keeps a rational place to park money.
A22: CARD LIST
A23: ID | B23: Card Name | C23: Type | D23: Polarity | E23: Magnitude | F23: Requirement | G23: Effect | H23: Flavor / Notes
A24: S01 | B24: YOU FORGOT TO EAT! | C24: Status | D24: Negative | E24: — | F24: Did not eat last turn | G24: -4 Time Units this turn | H24: Grab something at Regret Burger, Air One, or your fridge.
A25: S02 | B25: STRESSED OUT! | C25: Status | D25: Negative | E25: — | F25: No relaxation for 2 turns | G25: -2 Time Units this turn | H25: Stacks with S01; minimum 1 Time Unit per turn.
A26: S03 | B26: SAD PET | C26: Status | D26: Negative | E26: — | F26: Pet missed 1 feeding | G26: Pet Happiness -Standard (5%T) | H26: Feeding resets the missed-feeding counter.
A27: S04 | B27: STARVING PET | C27: Status | D27: Negative | E27: — | F27: Pet missed 2 consecutive feedings | G27: Pet Health -Strong (8%T), Pet Happiness -Strong (8%T) | H27: FINAL WARNING before pet death.
A28: S05 | B28: YOUR PET DIED | C28: Status | D28: Negative | E28: — | F28: Pet missed 3 consecutive feedings | G28: Pet removed; tombstone appears in player's housing; owner Happiness set to 0 | H28: Tombstone is permanent. Re-adoption allowed at Ethical Pet Shop (pet stats restart).
A29: I01 | B29: TO THE MOON! | C29: Investment | D29: Positive | E29: Major | F29: Holds Crypto | G29: Money +15%B | H29: Crypto big gain. Holding survives.
A30: I02 | B30: RUG PULL | C30: Investment | D30: Negative | E30: Major | F30: Holds Crypto | G30: CRYPTO HOLDING DESTROYED: principal (25%B) is lost. No further crypto cards until repurchased. | H30: Crypto big loss. This is the only outcome that destroys a holding.
A31: I03 | B31: CRYPTO WOBBLE | C31: Investment | D31: Mixed | E31: Minor | F31: Holds Crypto | G31: Money +5%B or -5%B per the odds table | H31: Crypto small swing. Holding survives.
A32: I04 | B32: BULL RUN | C32: Investment | D32: Positive | E32: Major | F32: Holds Stocks | G32: Money +8%B | H32: Stocks big gain.
A33: I05 | B33: MARKET DIP | C33: Investment | D33: Negative | E33: Minor | F33: Holds Stocks | G33: Money -3%B | H33: Stocks small loss.
A34: I06 | B34: DIVIDEND DAY | C34: Investment | D34: Positive | E34: Minor | F34: Holds Stocks | G34: Money +3%B | H34: Stocks small gain.
... A67: E29 | B67: NOISY NEIGHBORS | C67: Event | D67: Negative | E67: Minor | F67: Not homeless | G67: Happiness -Tiny (2.5%T) | H67: They discovered the karaoke machine.
A68: E30
A70: DESIGN GUARDRAILS: (1) Exactly 1 event card per player per turn — status and investment cards are extra but event-driven. (2) Event effects cap at Premium (12%T) so rubber-banding helps trailing players without deciding the game by itself. (3) Standing weights apply ONLY to card draws and investment resolution, never to base action gains. (4) Weekend Cards can be toggled off in Game Setup for testing.
A72: V4 RULES | B72: (1) Card effects are NEVER modified by personality, pet, item, or temporary modifiers, and ignore the 1.25x income cap — printed values apply exactly. (2) Exactly 1 event card per turn; status and investment cards are extra. (3) One investment card per HELD ASSET per turn. (4) A player holding all four assets sees four investment cards. (5) Turning Weekend Cards off never changes outcomes, only presentation — investments still resolve silently to the log.

Sheet Investments
A1: INVESTMENT ASSET LIFECYCLE (locked in v4). This sheet closes the largest open design gap: v3 never defined what a 'held asset' actually was.
A3: Asset | B3: Principal (cost) | C3: Per-turn outcome | D3: Standing-weighted? | E3: Can be destroyed? | F3: Max held | G3: Cash Out returns
A4: Savings | B4: 10%B | C4: +1%B guaranteed | D4: No | E4: No | F4: 1 | G4: 100% of principal (10%B)
A5: Bonds | B5: 15%B | C5: +2%B guaranteed | D5: No | E5: No | F5: 1 | G5: 100% of principal (15%B)
A6: Stocks | B6: 20%B | C6: Big gain +8%B / small gain +3%B / flat / small loss -3%B / big loss -8%B | D6: Yes (mild) | E6: No | F6: 1 | G6: 100% of principal (20%B)
A7: Crypto | B7: 25%B | C7: Big gain +15%B / small swing +/-5%B / RUG PULL destroys holding | D7: Yes (extreme) | E7: Yes — rug pull only | F7: 1 | G7: 100% of principal (25%B)
A9: RULES
A10: Does buying an asset give Money immediately? | B10: NO. The purchase cost is the principal being moved into the asset. v3's spreadsheet listed a Money gain on the purchase row, which would have double-counted; those gains are now 0.
A11: Does an asset persist? | B11: Yes. A holding stays until it is cashed out or destroyed, and draws one outcome card at the start of every one of the owner's turns.
A12: Can a player own more than one of the same asset? | B12: No. Maximum one holding per asset type. This is what prevents the savings/bonds spam exploit.
A13: Can a player own all four at once? | B13: Yes. All four can be held simultaneously, producing four investment cards per turn. Total principal for the full portfolio is 70%B.
A14: Can assets be sold? | B14: Yes. The Cash Out Investment action at Debtstreet Capital (1 Time Unit) sells one holding and returns 100% of its principal.
A15: Does a loss destroy the investment? | B15: Only a crypto RUG PULL destroys a holding (principal lost). Every other loss is a Money deduction; the holding survives and keeps drawing cards.
A16: What happens on a Big Loss if the player is INFORMED? | B16: The Big Loss is downgraded to a Small Loss and the INFORMED status is consumed. For crypto this means the holding is NOT destroyed.
A17: Do returns compound? | B17: No. Returns are always a flat percentage of B, never a percentage of accumulated winnings. This keeps late-game money bounded.
A18: Do card returns get personality/pet/item modifiers? | B18: No. See the card effect modifier rule in Settings.
A19: What if the player cannot afford the principal? | B19: The purchase action is unavailable (greyed out), like any other action they cannot afford.
A21: EXPECTED VALUE PER TURN (design check, %B)
A22: Asset | B22: Last place | C22: 2nd / 3rd | D22: 1st place | E22: Comment
A23: Savings | B23: +1.0 | C23: +1.0 | D23: +1.0 | E23: Flat and safe in every position
A24: Bonds | B24: +2.0 | C24: +2.0 | D24: +2.0 | E24: Flat and safe in every position
A25: Stocks | B25: +1.8 | C25: 0.0 | D25: -1.8 | E25: Mild tilt; genuinely neutral for mid-table
A26: Crypto | B26: +6.0 | C26: -1.3 | D26: -11.0 | E26: Extreme. A strong comeback tool and a real trap for the leader
A27: Read: the leader's rational play is bonds/savings; crypto is a gamble they should usually avoid or cash out. The trailing player has a genuine high-variance comeback lever. That is the intended shape.

Sheet Education_Paths
A1: HIGH IQ UNIVERSITY — 5 PATHS, 30 COURSES (new in v5). A 'click' is one study interaction costing 1 Time Unit. Course cost is paid once, on starting the course. Courses unlock strictly in order within a path; a path unlocks when the previous path is fully complete. Each course can be completed only once and greys out afterwards.
A3: Path | B3: Level Name | C3: Course # | D3: Course | E3: Cost $ (Short) | F3: Cost %B | G3: Clicks (Time Units) | H3: Unlocks job tier | I3: Critical Thinking gain | J3: Career gain
A4: 1 | B4: Technical Certification | C4: 1 | D4: Serving 101 | E4: 50 | F4: 0.5 | G4: 1 | H4: Low+ | I4: 0.02 | J4: 0.005
A5: 1 | B5: Technical Certification | C5: 2 | D5: Money Handling 101 | E5: 50 | F5: 0.5 | G5: 1 | H5: Low+ | I5: 0.02 | J5: 0.005
A6: 1 | B6: Technical Certification | C6: 3 | D6: Customer Service 101 | E6: 50 | F6: 0.5 | G6: 1 | H6: Low+ | I6: 0.02 | J6: 0.005
A7: 1 | B7: Technical Certification | C7: 4 | D7: Repairs 101 | E7: 50 | F7: 0.5 | G7: 1 | H7: Low+ | I7: 0.02 | J7: 0.005
A8: 1 | B8: Technical Certification | C8: 5 | D8: Maintenance 101 | E8: 50 | F8: 0.5 | G8: 1 | H8: Low+ | I8: 0.02 | J8: 0.005
A9: 1 | B9: Technical Certification | C9: 6 | D9: First Aid and CPR 101 | E9: 50 | F9: 0.5 | G9: 1 | H9: Low+ | I9: 0.02 | J9: 0.005
A10: 2 | B10: College Diploma | C10: 1 | D10: Marketing 201 | E10: 100 | F10: 1 | G10: 2 | H10: Mid | I10: 0.03 | J10: 0.01
A11: 2 | B11: College Diploma | C11: 2 | D11: Business Admin 201 | E11: 100 | F11: 1 | G11: 2 | H11: Mid | I11: 0.03 | J11: 0.01
A12: 2 | B12: College Diploma | C12: 3 | D12: Spreadsheet 201 | E12: 100 | F12: 1 | G12: 2 | H12: Mid | I12: 0.03 | J12: 0.01
A13: 2 | B13: College Diploma | C13: 4 | D13: Accounting 201 | E13: 100 | F13: 1 | G13: 2 | H13: Mid | I13: 0.03 | J13: 0.01
A14: 2 | B14: College Diploma | C14: 5 | D14: Human Resources 201 | E14: 100 | F14: 1 | G14: 2 | H14: Mid | I14: 0.03 | J14: 0.01
A15: 2 | B15: College Diploma | C15: 6 | D15: Economics 201 | E15: 100 | F15: 1 | G15: 2 | H15: Mid | I15: 0.03 | J15: 0.01
... A33: 5 | B33: PhD | C33: 6 | D33: Strategic Alliance 501 | E33: 250 | F33: 2.5 | G33: 5 | H33: Max | I33: 0.06 | J33: 0.025
A35: PATH TOTALS
A36: Path | B36: Level Name | C36: Total cost $ (Short) | D36: Total clicks / Time Units | E36: Required for | F36: Cumulative cost $ | G36: Cumulative clicks
A37: 1 | B37: Technical Certification | C37: 300 | D37: 6 | E37: Low+ tier jobs | F37: 300 | G37: 6
A38: 2 | B38: College Diploma | C38: 600 | D38: 12 | E38: Mid tier jobs | F38: 900 | G38: 18
A39: 3 | B39: College Degree | C39: 900 | D39: 18 | E39: Mid+ tier jobs | F39: 1800 | G39: 36
A40: 4 | B40: Master's Degree | C40: 1200 | D40: 24 | E40: High tier jobs | F40: 3000 | G40: 60
A41: 5 | B41: PhD | C41: 1500 | D41: 30 | E41: Max tier jobs | F41: 4500 | G41: 90
A43: UNLOCK RULES
A44: Order within a path | B44: Course 1 must be completed before course 2 becomes available, and so on. Completing a course immediately unlocks the next one in that path.
A45: Order between paths | B45: Path N+1 is locked until ALL SIX courses of path N are complete. Path 1 is available from the start of the game.
A46: Completed courses | B46: Greyed out and unselectable. Each course can be completed only once; a completed path can never be repeated or re-purchased.
A47: Partial progress | B47: Clicks accumulate on the course in progress. A course started but not finished keeps its progress between turns and must be finished before the next course unlocks.
A48: Payment | B48: The course cost is charged once, when the first click on that course is spent. If the player cannot afford it, the course is unavailable.
A49: Job gating | B49: Path 1 complete = eligible for Low+ jobs. Path 2 = Mid. Path 3 = Mid+. Path 4 = High. Path 5 = Max. Low tier jobs require no education. Education is necessary but NOT sufficient: the work-click requirement in Job_Progression must also be met.
A50: Fix from v4 | B50: The old Take Class / Finish Undergrad / Finish Master's / Finish PhD actions are REMOVED and replaced entirely by these 30 courses. This also fixes the bug where school courses were unavailable.
A52: CAREER GAIN HALVED IN v6 | B52: Career per course is now 0.5%B / 1%B / 1.5%B / 2%B / 2.5%B for paths 1-5 (path totals 3 / 6 / 9 / 12 / 15 = 45 points at Short, down from 90). Critical Thinking gains are unchanged. In v5 the 30 courses alone delivered 90% of a Short game's Career bar, which is most of why Career was trivial to max. Course Career gain is also subject to the per-turn diminishing-returns rule in Settings.

Sheet Job_Progression
A1: JOB TIER PROGRESSION (rebuilt in v5). Promotions are REMOVED. There is no requirement to stay in one job, and no promotion action. Instead, tier eligibility is earned by accumulating WORK CLICKS and completing EDUCATION PATHS. A work click = one Work action (2 Time Units). Clicks accumulate per tier, permanently, across every building.
A3: Target tier | B3: Work-click requirement | C3: Alternate route | D3: Education required | E3: Pay per click $ (Short) | F3: Pay %B | G3: Career gain per click (v6)
A4: Low | B4: None — entry tier | C4: — | D4: None | E4: 40 | F4: 0.4 | G4: 2
A5: Low+ | B5: 10 clicks at Low | C5: — | D5: Path 1 complete (Technical Certification) | E5: 65 | F5: 0.65 | G5: 2
A6: Mid | B6: 15 clicks at Low+ | C6: OR 20 clicks at Low | D6: Path 2 complete (College Diploma) | E6: 110 | F6: 1.1 | G6: 3
A7: Mid+ | B7: 20 clicks at Mid | C7: — | D7: Path 3 complete (College Degree) | E7: 170 | F7: 1.7 | G7: 3
A8: High | B8: 25 clicks at Mid+ | C8: OR 30 clicks at Mid | D8: Path 4 complete (Master's Degree) | E8: 260 | F8: 2.6 | G8: 4
A9: Max | B9: 40 clicks at High | C9: — | D9: Path 5 complete (PhD) | E9: 400 | F9: 4 | G9: 5
A11: RULES
A12: Both conditions required | B12: A tier unlocks only when BOTH the work-click count AND the education path are satisfied. Either one alone is not enough.
A13: No promotion action | B13: Ask for Promotion is removed from Corporate Soul Exchange. Players change jobs freely at the job board whenever they are eligible.
A14: No loyalty requirement | B14: There is no minimum time in a job before moving to another job, in the same building or any other.
A15: Clicks are per tier | B15: Work clicks are counted against the tier of the job that was worked. Working a Low job accumulates Low clicks even after Low+ is unlocked.
A16: Clicks are global | B16: Clicks accumulate across every building. Ten Low clicks at Regret Burger and zero elsewhere still satisfies the Low+ gate.
A17: Alternate routes | B17: Mid and High have a slower alternate route from the tier below the expected one, so a player who skipped a tier is not permanently blocked.
A18: Total to Max tier | B18: 10 + 15 + 20 + 25 + 40 = 110 work clicks (220 Time Units) plus 90 study clicks (90 Time Units). See the pacing warning below.
A20: PACING WARNING — NEEDS A DECISION BEFORE BUILD
A21: The click gates above are absolute numbers, so they do not shrink in shorter games. Reaching Max tier costs 220 Time Units of work plus 90 of study = 310 Time Units. At 6 Time Units per turn, and with players also needing to eat, relax, pay rent and travel, that is roughly 70-90 turns of near-total career focus. A Short game (20 uses to max a stat) will realistically never reach High or Max tier.
A22: OPTION A (as specified, default in this file) | B22: Keep absolute gates. Short games are capped in practice at Low+/Mid tier; High and Max become Long-game achievements. Simple, and makes the tiers feel earned.
A23: OPTION B (recommended alternative) | B23: Scale the gates by mode so every length can reach the top: Short = 40% of the listed clicks, Medium = 70%, Long = 100%. Example for Low+: 4 clicks Short, 7 Medium, 10 Long.
A25: Mode-scaled gates if Option B is chosen
A26: Target tier | B26: Long (100%) | C26: Medium (70%) | D26: Short (40%)
A27: Low+ | B27: 10 | C27: 7 | D27: 4
A28: Mid | B28: 15 | C28: 10 | D28: 6
A29: Mid+ | B29: 20 | C29: 14 | D29: 8
A30: High | B30: 25 | C30: 18 | D30: 10
A31: Max | B31: 40 | C31: 28 | D31: 16
A33: CAREER PATCH v6 | B33: Career gain per work click is set here and in Jobs_Named, and nowhere else. It was 3 / 5 / 7 / 10 by tier in v5 and is now 2 / 2 / 3 / 3 / 4 / 5 across the six tiers. The Work rows in Actions_Master no longer grant Career at all.
A34: Per-turn diminishing returns | B34: Within one turn, the 1st Career-granting action gives 100% of its value, the 2nd gives 50%, the 3rd 25%, and the 4th and later 10%. Rounded down, minimum 1 point per action. This applies to every Career source — work clicks, Work From Home, university courses, and the Corporate side actions — in the order taken. It does NOT apply to Money, to any other stat, or to card effects.
A35: What that does | B35: Three work clicks at Mid tier used to be +18 Career a turn (and +30 with resume spam). It is now 3 + 1.5 + 0.75 = 5 points. Maxing Career at the Short cap of 100 goes from under 4 turns of focus to roughly 20 — the same order of magnitude as the other three main stats.
A36: DECISION STILL OPEN | B36: Option A vs Option B on the click gates above is still unresolved. With the v6 turn limit, OPTION B (Short 40% / Medium 70% / Long 100%) is now the recommended choice: a 20-turn game cannot reach 110 work clicks under Option A, so the top half of the freshly re-ordered job ladder would be visible but permanently unreachable.

Sheet Build_Notes
A1: BUILD NOTES v6.1 — what the live build does beyond Balance Lock v6. Keep this sheet when generating the next version.
A2: Rule | B2: What the build does | C2: Why / origin
A3: Time Units per turn | B3: 40 by default, chosen on Game Setup (12-50) | C3: Austin's 2026-07-06 call. The sheet's pacing math assumes 6, so anything written as 'per turn' is far weaker in play.
A4: Career in practice | B4: v6 curve implemented exactly (100/50/25/10, min 1) | C4: At 40 TU a player takes ~20 work clicks a turn, so Career still maxes around round 8. Lowering Time Units per turn is the lever.
A5: Hunger / stress | B5: 25% and 15% of the turn's Time Units; stress also costs 5%B Health and Happiness | C5: Chosen 2026-07-20, harsher than the flat -4 / -2 in the sheet.
A6: Starting money | B6: $200 (2 x B), starting item Casual Clothes | C6: Mirrors the Homeless Support Cheque so turn 1 is playable.
A7: Move-in and re-housing | B7: 1.5 x that tier's rent (Low $150, Luxury $600) | C7: Deposit plus the first cycle's rent. Not specified in the sheet.
A8: Pay Rent | B8: Always listed; four states; may be pre-paid, and a pre-payment survives the rent turn | C8: v6 spec implemented; pre-payment needed a rentPaidThrough marker so the rent-turn reset does not wipe it.
A9: Final score | B9: Money counts at most T; the wallet itself stays uncapped | C9: Without this, v5's dollar economy let hoarded cash push scores past the 6T maximum.
A10: Club jobs | B10: Coat Check, Bouncer and Bartender require the club dress code before you can take them | C10: Playtest bug: you could take a club job, never get past the bouncer, and be fired for missing every shift.
A11: Play With Pet (Heelton) | B11: Added so Pet Bed and Pet Toys can fire in the luxury flat | C11: The sheet only gives Hang With Pet at Low Cost Housing.
A12: Other build-only actions | B12: Eat at Home, Feed Pet (Heelton), Cash Out Investment, Re-house, Switch housing, three Coolness extras | C12: Rules the manual describes but the sheet has no row for.
A13: Work From Home | B13: Counts as a work click and pays the job tier x 0.85 | C13: v6 spec implemented.
... A25: PRICES RESTORED IN v6.1 | B25: v6 was generated from the original v5 and reverted prices approved on 2026-09-16/17. | C25: See the Actions_Master Balance Notes marked v6.1.
